{
  "vectorCommands": [
    { "command": "PicSetColor", "args": [0] },
    { "command": "DrawFill", "args": [49, 119] },
    { "command": "PicSetColor", "args": [7] },
    { "command": "DrawAbs", "args": [46, 109, 47, 109] },
    { "command": "DrawAbs", "args": [46, 110, 47, 110] },
    { "command": "DrawAbs", "args": [46, 111, 47, 111] },
    { "command": "DrawAbs", "args": [46, 106, 47, 106] },
    { "command": "DrawAbs", "args": [46, 107, 47, 107] },
    { "command": "DrawAbs", "args": [46, 106, 47, 106] },
    { "command": "DrawAbs", "args": [46, 107, 47, 107] },
    { "command": "DrawAbs", "args": [46, 106, 47, 106] },
    { "command": "DrawAbs", "args": [46, 107, 47, 107] },
    { "command": "DrawAbs", "args": [46, 106, 47, 106] },
    { "command": "DrawAbs", "args": [46, 107, 47, 107] },
    { "command": "DrawAbs", "args": [46, 108, 47, 108] },
    { "command": "DrawAbs", "args": [46, 109, 47, 109] },
    { "command": "DrawAbs", "args": [47, 104, 48, 104] },
    { "command": "DrawAbs", "args": [46, 105, 47, 105] },
    { "command": "DrawAbs", "args": [47, 112, 48, 112] },
    { "command": "DrawAbs", "args": [48, 112, 49, 112] },
    { "command": "DrawAbs", "args": [48, 113, 49, 113] },
    { "command": "DrawAbs", "args": [48, 103, 49, 103] },
    { "command": "DrawAbs", "args": [48, 104, 49, 104] },
    { "command": "DrawAbs", "args": [49, 104, 50, 104] },
    { "command": "DrawAbs", "args": [49, 105, 50, 105] },
    { "command": "DrawAbs", "args": [49, 112, 50, 112] },
    { "command": "DrawAbs", "args": [49, 111, 50, 111] },
    { "command": "DrawAbs", "args": [52, 103, 53, 103] },
    { "command": "DrawAbs", "args": [52, 104, 53, 104] },
    { "command": "DrawAbs", "args": [52, 105, 53, 105] },
    { "command": "DrawAbs", "args": [52, 106, 53, 106] },
    { "command": "DrawAbs", "args": [52, 107, 53, 107] },
    { "command": "DrawAbs", "args": [52, 108, 53, 108] },
    { "command": "DrawAbs", "args": [52, 109, 53, 109] },
    { "command": "DrawAbs", "args": [52, 110, 53, 110] },
    { "command": "DrawAbs", "args": [52, 111, 53, 111] },
    { "command": "DrawAbs", "args": [52, 112, 53, 112] },
    { "command": "DrawAbs", "args": [52, 113, 53, 113] },
    { "command": "DrawAbs", "args": [54, 103, 55, 103] },
    { "command": "DrawAbs", "args": [54, 108, 55, 108] },
    { "command": "DrawAbs", "args": [55, 104, 56, 104] },
    { "command": "DrawAbs", "args": [55, 105, 56, 105] },
    { "command": "DrawAbs", "args": [55, 104, 56, 104] },
    { "command": "DrawAbs", "args": [55, 105, 56, 105] },
    { "command": "DrawAbs", "args": [55, 106, 56, 106] },
    { "command": "DrawAbs", "args": [55, 107, 56, 107] },
    { "command": "DrawAbs", "args": [55, 109, 56, 109] },
    { "command": "DrawAbs", "args": [55, 110, 56, 110] },
    { "command": "DrawAbs", "args": [55, 111, 56, 111] },
    { "command": "DrawAbs", "args": [55, 112, 56, 112] },
    { "command": "DrawAbs", "args": [55, 113, 56, 113] },
    { "command": "DrawAbs", "args": [58, 113, 59, 113] },
    { "command": "DrawAbs", "args": [58, 112, 59, 112] },
    { "command": "DrawAbs", "args": [58, 111, 59, 111] },
    { "command": "DrawAbs", "args": [58, 110, 59, 110] },
    { "command": "DrawAbs", "args": [58, 108, 59, 108] },
    { "command": "DrawAbs", "args": [58, 107, 59, 107] },
    { "command": "DrawAbs", "args": [58, 108, 59, 108] },
    { "command": "DrawAbs", "args": [58, 109, 59, 109] },
    { "command": "DrawAbs", "args": [58, 110, 59, 110] },
    { "command": "DrawAbs", "args": [58, 109, 59, 109] },
    { "command": "DrawAbs", "args": [58, 108, 59, 108] },
    { "command": "DrawAbs", "args": [58, 107, 59, 107] },
    { "command": "DrawAbs", "args": [58, 106, 59, 106] },
    { "command": "DrawAbs", "args": [58, 105, 59, 105] },
    { "command": "DrawAbs", "args": [58, 104, 59, 104] },
    { "command": "DrawAbs", "args": [59, 103, 60, 103] },
    { "command": "DrawAbs", "args": [60, 103, 61, 103] },
    { "command": "DrawAbs", "args": [61, 105, 62, 105] },
    { "command": "DrawAbs", "args": [61, 104, 62, 104] },
    { "command": "DrawAbs", "args": [61, 105, 62, 105] },
    { "command": "DrawAbs", "args": [61, 106, 62, 106] },
    { "command": "DrawAbs", "args": [61, 107, 62, 107] },
    { "command": "DrawAbs", "args": [61, 108, 62, 108] },
    { "command": "DrawAbs", "args": [61, 109, 62, 109] },
    { "command": "DrawAbs", "args": [61, 110, 62, 110] },
    { "command": "DrawAbs", "args": [61, 111, 62, 111] },
    { "command": "DrawAbs", "args": [61, 112, 62, 112] },
    { "command": "DrawAbs", "args": [61, 113, 62, 113] },
    { "command": "DrawAbs", "args": [60, 109, 61, 109] },
    { "command": "DrawAbs", "args": [64, 103, 65, 103] },
    { "command": "DrawAbs", "args": [64, 104, 65, 104] },
    { "command": "DrawAbs", "args": [64, 105, 65, 105] },
    { "command": "DrawAbs", "args": [64, 106, 65, 106] },
    { "command": "DrawAbs", "args": [64, 107, 65, 107] },
    { "command": "DrawAbs", "args": [64, 108, 65, 108] },
    { "command": "DrawAbs", "args": [64, 109, 65, 109] },
    { "command": "DrawAbs", "args": [64, 110, 65, 110] },
    { "command": "DrawAbs", "args": [64, 111, 65, 111] },
    { "command": "DrawAbs", "args": [64, 112, 65, 112] },
    { "command": "DrawAbs", "args": [64, 113, 65, 113] },
    { "command": "DrawAbs", "args": [66, 103, 67, 103] },
    { "command": "DrawAbs", "args": [69, 103, 70, 103] },
    { "command": "DrawAbs", "args": [71, 103, 72, 103] },
    { "command": "DrawAbs", "args": [70, 103, 71, 103] },
    { "command": "DrawAbs", "args": [70, 104, 71, 104] },
    { "command": "DrawAbs", "args": [70, 105, 71, 105] },
    { "command": "DrawAbs", "args": [70, 106, 71, 106] },
    { "command": "DrawAbs", "args": [70, 107, 71, 107] },
    { "command": "DrawAbs", "args": [70, 108, 71, 108] },
    { "command": "DrawAbs", "args": [70, 109, 71, 109] },
    { "command": "DrawAbs", "args": [70, 110, 71, 110] },
    { "command": "DrawAbs", "args": [70, 111, 71, 111] },
    { "command": "DrawAbs", "args": [70, 112, 71, 112] },
    { "command": "DrawAbs", "args": [70, 113, 71, 113] },
    { "command": "DrawAbs", "args": [74, 103, 75, 103] },
    { "command": "DrawAbs", "args": [74, 104, 75, 104] },
    { "command": "DrawAbs", "args": [74, 105, 75, 105] },
    { "command": "DrawAbs", "args": [74, 106, 75, 106] },
    { "command": "DrawAbs", "args": [74, 107, 75, 107] },
    { "command": "DrawAbs", "args": [74, 108, 75, 108] },
    { "command": "DrawAbs", "args": [74, 109, 75, 109] },
    { "command": "DrawAbs", "args": [74, 110, 75, 110] },
    { "command": "DrawAbs", "args": [74, 111, 75, 111] },
    { "command": "DrawAbs", "args": [74, 112, 75, 112] },
    { "command": "DrawAbs", "args": [74, 113, 75, 113] },
    { "command": "DrawAbs", "args": [76, 103, 77, 103] },
    { "command": "DrawAbs", "args": [79, 103, 80, 103] },
    { "command": "DrawAbs", "args": [79, 104, 80, 104] },
    { "command": "DrawAbs", "args": [79, 105, 80, 105] },
    { "command": "DrawAbs", "args": [79, 106, 80, 106] },
    { "command": "DrawAbs", "args": [79, 107, 80, 107] },
    { "command": "DrawAbs", "args": [79, 108, 80, 108] },
    { "command": "DrawAbs", "args": [79, 109, 80, 109] },
    { "command": "DrawAbs", "args": [79, 110, 80, 110] },
    { "command": "DrawAbs", "args": [79, 111, 80, 111] },
    { "command": "DrawAbs", "args": [79, 112, 80, 112] },
    { "command": "DrawAbs", "args": [79, 113, 80, 113] },
    { "command": "DrawAbs", "args": [81, 103, 82, 103] },
    { "command": "DrawAbs", "args": [82, 104, 83, 104] },
    { "command": "DrawAbs", "args": [82, 105, 83, 105] },
    { "command": "DrawAbs", "args": [82, 106, 83, 106] },
    { "command": "DrawAbs", "args": [82, 107, 83, 107] },
    { "command": "DrawAbs", "args": [82, 108, 83, 108] },
    { "command": "DrawAbs", "args": [81, 109, 82, 109] },
    { "command": "DrawAbs", "args": [82, 111, 83, 111] },
    { "command": "DrawAbs", "args": [82, 110, 83, 110] },
    { "command": "DrawAbs", "args": [82, 111, 83, 111] },
    { "command": "DrawAbs", "args": [82, 112, 83, 112] },
    { "command": "DrawAbs", "args": [82, 113, 83, 113] },
    { "command": "DrawAbs", "args": [66, 109, 67, 109] },
    { "command": "DrawAbs", "args": [76, 109, 77, 109] },
    { "command": "DrawAbs", "args": [76, 113, 77, 113] },
    { "command": "PicSetColor", "args": [4] },
    { "command": "DrawAbs", "args": [43, 105, 44, 105] },
    { "command": "DrawAbs", "args": [43, 106, 44, 106] },
    { "command": "DrawAbs", "args": [43, 107, 44, 107] },
    { "command": "DrawAbs", "args": [43, 108, 44, 108] },
    { "command": "DrawAbs", "args": [43, 109, 44, 109] },
    { "command": "DrawAbs", "args": [43, 110, 44, 110] },
    { "command": "DrawAbs", "args": [43, 111, 44, 111] },
    { "command": "DrawAbs", "args": [43, 112, 44, 112] },
    { "command": "DrawAbs", "args": [44, 112, 45, 112] },
    { "command": "DrawAbs", "args": [44, 113, 45, 113] },
    { "command": "DrawAbs", "args": [45, 114, 46, 114] },
    { "command": "DrawAbs", "args": [46, 115, 47, 115] },
    { "command": "DrawAbs", "args": [48, 116, 49, 116] },
    { "command": "DrawAbs", "args": [48, 115, 49, 115] },
    { "command": "DrawAbs", "args": [49, 115, 50, 115] },
    { "command": "DrawAbs", "args": [49, 116, 50, 116] },
    { "command": "DrawAbs", "args": [48, 116, 49, 116] },
    { "command": "DrawAbs", "args": [48, 115, 49, 115] },
    { "command": "DrawAbs", "args": [44, 104, 45, 104] },
    { "command": "DrawAbs", "args": [44, 103, 45, 103] },
    { "command": "DrawAbs", "args": [45, 103, 46, 103] },
    { "command": "DrawAbs", "args": [45, 102, 46, 102] },
    { "command": "DrawAbs", "args": [46, 102, 47, 102] },
    { "command": "DrawAbs", "args": [46, 101, 47, 101] },
    { "command": "DrawAbs", "args": [47, 101, 48, 101] },
    { "command": "DrawAbs", "args": [48, 101, 49, 101] },
    { "command": "DrawAbs", "args": [49, 101, 50, 101] },
    { "command": "DrawAbs", "args": [50, 102, 51, 102] },
    { "command": "DrawAbs", "args": [50, 100, 51, 100] },
    { "command": "DrawAbs", "args": [50, 101, 51, 101] },
    { "command": "DrawAbs", "args": [49, 99, 50, 99] },
    { "command": "DrawAbs", "args": [49, 100, 50, 100] },
    { "command": "DrawAbs", "args": [48, 100, 49, 100] },
    { "command": "DrawAbs", "args": [48, 99, 49, 99] },
    { "command": "DrawAbs", "args": [47, 99, 48, 99] },
    { "command": "DrawAbs", "args": [47, 100, 48, 100] },
    { "command": "DrawAbs", "args": [46, 100, 47, 100] },
    { "command": "DrawAbs", "args": [46, 99, 47, 99] },
    { "command": "DrawAbs", "args": [45, 99, 46, 99] },
    { "command": "DrawAbs", "args": [45, 100, 46, 100] },
    { "command": "DrawAbs", "args": [44, 100, 45, 100] },
    { "command": "DrawAbs", "args": [44, 101, 45, 101] },
    { "command": "DrawAbs", "args": [45, 101, 46, 101] },
    { "command": "DrawAbs", "args": [44, 101, 45, 101] },
    { "command": "DrawAbs", "args": [44, 102, 45, 102] },
    { "command": "DrawAbs", "args": [43, 102, 44, 102] },
    { "command": "DrawAbs", "args": [43, 103, 44, 103] },
    { "command": "DrawAbs", "args": [43, 104, 44, 104] },
    { "command": "DrawAbs", "args": [43, 105, 44, 105] },
    { "command": "DrawAbs", "args": [42, 106, 43, 106] },
    { "command": "DrawAbs", "args": [42, 107, 43, 107] },
    { "command": "DrawAbs", "args": [42, 108, 43, 108] },
    { "command": "DrawAbs", "args": [42, 109, 43, 109] },
    { "command": "DrawAbs", "args": [42, 110, 43, 110] },
    { "command": "DrawAbs", "args": [43, 110, 44, 110] },
    { "command": "DrawAbs", "args": [43, 111, 44, 111] },
    { "command": "DrawAbs", "args": [43, 112, 44, 112] },
    { "command": "DrawAbs", "args": [44, 113, 45, 113] },
    { "command": "DrawAbs", "args": [44, 114, 45, 114] },
    { "command": "DrawAbs", "args": [44, 115, 45, 115] },
    { "command": "DrawAbs", "args": [44, 116, 45, 116] },
    { "command": "DrawAbs", "args": [45, 116, 46, 116] },
    { "command": "DrawAbs", "args": [45, 117, 46, 117] },
    { "command": "DrawAbs", "args": [46, 117, 47, 117] },
    { "command": "DrawAbs", "args": [46, 116, 47, 116] },
    { "command": "DrawAbs", "args": [47, 116, 48, 116] },
    { "command": "DrawAbs", "args": [47, 115, 48, 115] },
    { "command": "DrawAbs", "args": [47, 116, 48, 116] },
    { "command": "DrawAbs", "args": [47, 117, 48, 117] },
    { "command": "DrawAbs", "args": [47, 118, 48, 118] },
    { "command": "DrawAbs", "args": [48, 118, 49, 118] },
    { "command": "DrawAbs", "args": [48, 117, 49, 117] },
    { "command": "DrawAbs", "args": [48, 116, 49, 116] },
    { "command": "DrawAbs", "args": [43, 114, 44, 114] },
    { "command": "DrawAbs", "args": [43, 113, 44, 113] },
    { "command": "DrawAbs", "args": [42, 111, 43, 111] },
    { "command": "DrawAbs", "args": [42, 107, 43, 107] },
    { "command": "DrawAbs", "args": [42, 106, 43, 106] },
    { "command": "DrawAbs", "args": [43, 106, 44, 106] },
    { "command": "DrawAbs", "args": [43, 105, 44, 105] },
    { "command": "DrawAbs", "args": [43, 104, 44, 104] },
    { "command": "DrawAbs", "args": [43, 105, 44, 105] },
    { "command": "DrawAbs", "args": [42, 105, 43, 105] },
    { "command": "DrawAbs", "args": [43, 105, 44, 105] },
    { "command": "DrawAbs", "args": [43, 104, 44, 104] },
    { "command": "DrawAbs", "args": [42, 104, 43, 104] },
    { "command": "DrawAbs", "args": [42, 103, 43, 103] },
    { "command": "DrawAbs", "args": [47, 98, 48, 98] },
    { "command": "DrawAbs", "args": [47, 97, 48, 97] },
    { "command": "DrawAbs", "args": [44, 97, 45, 97] },
    { "command": "DrawAbs", "args": [44, 98, 45, 98] },
    { "command": "DrawAbs", "args": [44, 99, 45, 99] },
    { "command": "DrawAbs", "args": [45, 99, 46, 99] },
    { "command": "DrawAbs", "args": [44, 99, 45, 99] },
    { "command": "DrawAbs", "args": [42, 100, 43, 100] },
    { "command": "DrawAbs", "args": [42, 101, 43, 101] },
    { "command": "DrawAbs", "args": [43, 101, 44, 101] },
    { "command": "DrawAbs", "args": [43, 102, 44, 102] },
    { "command": "DrawAbs", "args": [44, 102, 45, 102] },
    { "command": "DrawAbs", "args": [44, 103, 45, 103] },
    { "command": "DrawAbs", "args": [44, 104, 45, 104] },
    { "command": "DrawAbs", "args": [40, 106, 41, 106] },
    { "command": "DrawAbs", "args": [40, 107, 41, 107] },
    { "command": "DrawAbs", "args": [41, 107, 42, 107] },
    { "command": "DrawAbs", "args": [40, 107, 41, 107] },
    { "command": "DrawAbs", "args": [40, 106, 41, 106] },
    { "command": "DrawAbs", "args": [42, 111, 43, 111] },
    { "command": "DrawAbs", "args": [41, 111, 42, 111] },
    { "command": "DrawAbs", "args": [41, 112, 42, 112] },
    { "command": "DrawAbs", "args": [41, 113, 42, 113] },
    { "command": "DrawAbs", "args": [44, 116, 45, 116] },
    { "command": "DrawAbs", "args": [43, 116, 44, 116] },
    { "command": "DrawAbs", "args": [43, 117, 44, 117] },
    { "command": "DrawAbs", "args": [43, 118, 44, 118] },
    { "command": "DrawAbs", "args": [46, 117, 47, 117] },
    { "command": "DrawAbs", "args": [46, 118, 47, 118] },
    { "command": "DrawAbs", "args": [47, 118, 48, 118] },
    { "command": "DrawAbs", "args": [47, 119, 48, 119] },
    { "command": "DrawAbs", "args": [47, 120, 48, 120] },
    { "command": "DrawAbs", "args": [47, 121, 48, 121] },
    { "command": "DrawAbs", "args": [41, 106, 42, 106] },
    { "command": "DrawAbs", "args": [41, 107, 42, 107] },
    { "command": "DrawAbs", "args": [41, 108, 42, 108] },
    { "command": "PicSetColor", "args": [15] },
    { "command": "DrawAbs", "args": [85, 104, 86, 104] },
    { "command": "DrawAbs", "args": [85, 105, 86, 105] },
    { "command": "DrawAbs", "args": [85, 106, 86, 106] },
    { "command": "DrawAbs", "args": [85, 107, 86, 107] },
    { "command": "DrawAbs", "args": [85, 108, 86, 108] },
    { "command": "DrawAbs", "args": [85, 109, 86, 109] },
    { "command": "DrawAbs", "args": [85, 108, 86, 108] },
    { "command": "DrawAbs", "args": [85, 109, 86, 109] },
    { "command": "DrawAbs", "args": [85, 110, 86, 110] },
    { "command": "DrawAbs", "args": [85, 111, 86, 111] },
    { "command": "DrawAbs", "args": [85, 112, 86, 112] },
    { "command": "DrawAbs", "args": [87, 113, 88, 113] },
    { "command": "DrawAbs", "args": [86, 103, 87, 103] },
    { "command": "DrawAbs", "args": [87, 103, 88, 103] },
    { "command": "DrawAbs", "args": [86, 113, 87, 113] },
    { "command": "DrawAbs", "args": [90, 103, 91, 103] },
    { "command": "DrawAbs", "args": [90, 104, 91, 104] },
    { "command": "DrawAbs", "args": [90, 105, 91, 105] },
    { "command": "DrawAbs", "args": [90, 106, 91, 106] },
    { "command": "DrawAbs", "args": [90, 107, 91, 107] },
    { "command": "DrawAbs", "args": [90, 108, 91, 108] },
    { "command": "DrawAbs", "args": [90, 109, 91, 109] },
    { "command": "DrawAbs", "args": [90, 110, 91, 110] },
    { "command": "DrawAbs", "args": [90, 111, 91, 111] },
    { "command": "DrawAbs", "args": [90, 112, 91, 112] },
    { "command": "DrawAbs", "args": [90, 113, 91, 113] },
    { "command": "DrawAbs", "args": [90, 112, 91, 112] },
    { "command": "DrawAbs", "args": [92, 104, 93, 104] },
    { "command": "DrawAbs", "args": [93, 105, 94, 105] },
    { "command": "DrawAbs", "args": [93, 106, 94, 106] },
    { "command": "DrawAbs", "args": [93, 107, 94, 107] },
    { "command": "DrawAbs", "args": [94, 104, 95, 104] },
    { "command": "DrawAbs", "args": [95, 103, 96, 103] },
    { "command": "DrawAbs", "args": [96, 103, 97, 103] },
    { "command": "DrawAbs", "args": [96, 104, 97, 104] },
    { "command": "DrawAbs", "args": [96, 105, 97, 105] },
    { "command": "DrawAbs", "args": [96, 106, 97, 106] },
    { "command": "DrawAbs", "args": [96, 107, 97, 107] },
    { "command": "DrawAbs", "args": [96, 108, 97, 108] },
    { "command": "DrawAbs", "args": [96, 109, 97, 109] },
    { "command": "DrawAbs", "args": [96, 110, 97, 110] },
    { "command": "DrawAbs", "args": [96, 111, 97, 111] },
    { "command": "DrawAbs", "args": [96, 112, 97, 112] },
    { "command": "DrawAbs", "args": [96, 110, 97, 110] },
    { "command": "DrawAbs", "args": [96, 111, 97, 111] },
    { "command": "DrawAbs", "args": [96, 112, 97, 112] },
    { "command": "DrawAbs", "args": [96, 113, 97, 113] },
    { "command": "DrawAbs", "args": [91, 103, 92, 103] },
    { "command": "DrawAbs", "args": [99, 104, 100, 104] },
    { "command": "DrawAbs", "args": [99, 105, 100, 105] },
    { "command": "DrawAbs", "args": [99, 106, 100, 106] },
    { "command": "DrawAbs", "args": [99, 107, 100, 107] },
    { "command": "DrawAbs", "args": [99, 108, 100, 108] },
    { "command": "DrawAbs", "args": [100, 103, 101, 103] },
    { "command": "DrawAbs", "args": [99, 107, 100, 107] },
    { "command": "DrawAbs", "args": [100, 109, 101, 109] },
    { "command": "DrawAbs", "args": [102, 103, 103, 103] },
    { "command": "DrawAbs", "args": [101, 109, 102, 109] },
    { "command": "DrawAbs", "args": [102, 109, 103, 109] },
    { "command": "DrawAbs", "args": [103, 110, 104, 110] },
    { "command": "DrawAbs", "args": [103, 111, 104, 111] },
    { "command": "PicSetColor", "args": [15] },
    { "command": "DrawAbs", "args": [99, 113, 100, 113] },
    { "command": "DrawAbs", "args": [101, 113, 102, 113] },
    { "command": "DrawAbs", "args": [103, 111, 104, 111] },
    { "command": "DrawAbs", "args": [103, 112, 104, 112] },
    { "command": "DrawAbs", "args": [102, 113, 103, 113] },
    { "command": "DrawAbs", "args": [103, 105, 104, 105] },
    { "command": "DrawAbs", "args": [103, 104, 104, 104] },
    { "command": "DrawAbs", "args": [99, 112, 100, 112] },
    { "command": "PicSetColor", "args": [9] },
    { "command": "DrawAbs", "args": [48, 25, 49, 25] },
    { "command": "DrawAbs", "args": [48, 26, 49, 26] },
    { "command": "DrawAbs", "args": [47, 26, 48, 26] },
    { "command": "DrawAbs", "args": [47, 27, 48, 27] },
    { "command": "DrawAbs", "args": [46, 27, 47, 27] },
    { "command": "DrawAbs", "args": [46, 28, 47, 28] },
    { "command": "DrawAbs", "args": [46, 29, 47, 29] },
    { "command": "DrawAbs", "args": [45, 29, 46, 29] },
    { "command": "DrawAbs", "args": [45, 30, 46, 30] },
    { "command": "DrawAbs", "args": [45, 31, 46, 31] },
    { "command": "DrawAbs", "args": [45, 32, 46, 32] },
    { "command": "DrawAbs", "args": [45, 33, 46, 33] },
    { "command": "DrawAbs", "args": [45, 34, 46, 34] },
    { "command": "DrawAbs", "args": [45, 35, 46, 35] },
    { "command": "DrawAbs", "args": [45, 36, 46, 36] },
    { "command": "DrawAbs", "args": [44, 36, 45, 36] },
    { "command": "DrawAbs", "args": [44, 37, 45, 37] },
    { "command": "DrawAbs", "args": [44, 38, 45, 38] },
    { "command": "DrawAbs", "args": [44, 39, 45, 39] },
    { "command": "DrawAbs", "args": [44, 40, 45, 40] },
    { "command": "DrawAbs", "args": [44, 41, 45, 41] },
    { "command": "DrawAbs", "args": [44, 42, 45, 42] },
    { "command": "DrawAbs", "args": [44, 43, 45, 43] },
    { "command": "DrawAbs", "args": [44, 44, 45, 44] },
    { "command": "DrawAbs", "args": [44, 45, 45, 45] },
    { "command": "DrawAbs", "args": [44, 46, 45, 46] },
    { "command": "DrawAbs", "args": [43, 46, 44, 46] },
    { "command": "DrawAbs", "args": [43, 47, 44, 47] },
    { "command": "DrawAbs", "args": [43, 48, 44, 48] },
    { "command": "DrawAbs", "args": [43, 49, 44, 49] },
    { "command": "DrawAbs", "args": [43, 50, 44, 50] },
    { "command": "DrawAbs", "args": [43, 51, 44, 51] },
    { "command": "DrawAbs", "args": [42, 51, 43, 51] },
    { "command": "DrawAbs", "args": [42, 52, 43, 52] },
    { "command": "DrawAbs", "args": [42, 53, 43, 53] },
    { "command": "DrawAbs", "args": [42, 54, 43, 54] },
    { "command": "DrawAbs", "args": [42, 55, 43, 55] },
    { "command": "DrawAbs", "args": [42, 56, 43, 56] },
    { "command": "DrawAbs", "args": [42, 57, 43, 57] },
    { "command": "DrawAbs", "args": [41, 57, 42, 57] },
    { "command": "DrawAbs", "args": [41, 58, 42, 58] },
    { "command": "DrawAbs", "args": [41, 59, 42, 59] },
    { "command": "DrawAbs", "args": [41, 60, 42, 60] },
    { "command": "DrawAbs", "args": [41, 61, 42, 61] },
    { "command": "DrawAbs", "args": [41, 62, 42, 62] },
    { "command": "DrawAbs", "args": [41, 63, 42, 63] },
    { "command": "DrawAbs", "args": [40, 64, 41, 64] },
    { "command": "DrawAbs", "args": [40, 65, 41, 65] },
    { "command": "DrawAbs", "args": [40, 66, 41, 66] },
    { "command": "DrawAbs", "args": [40, 67, 41, 67] },
    { "command": "DrawAbs", "args": [40, 68, 41, 68] },
    { "command": "DrawAbs", "args": [39, 69, 40, 69] },
    { "command": "DrawAbs", "args": [39, 70, 40, 70] },
    { "command": "DrawAbs", "args": [40, 70, 41, 70] },
    { "command": "DrawAbs", "args": [41, 70, 42, 70] },
    { "command": "DrawAbs", "args": [41, 71, 42, 71] },
    { "command": "DrawAbs", "args": [42, 71, 43, 71] },
    { "command": "DrawAbs", "args": [42, 72, 43, 72] },
    { "command": "DrawAbs", "args": [43, 72, 44, 72] },
    { "command": "DrawAbs", "args": [44, 72, 45, 72] },
    { "command": "DrawAbs", "args": [45, 72, 46, 72] },
    { "command": "DrawAbs", "args": [46, 72, 47, 72] },
    { "command": "DrawAbs", "args": [47, 72, 48, 72] },
    { "command": "DrawAbs", "args": [48, 72, 49, 72] },
    { "command": "DrawAbs", "args": [49, 72, 50, 72] },
    { "command": "DrawAbs", "args": [50, 72, 51, 72] },
    { "command": "DrawAbs", "args": [51, 72, 52, 72] },
    { "command": "DrawAbs", "args": [51, 71, 52, 71] },
    { "command": "DrawAbs", "args": [51, 70, 52, 70] },
    { "command": "DrawAbs", "args": [51, 69, 52, 69] },
    { "command": "DrawAbs", "args": [52, 69, 53, 69] },
    { "command": "DrawAbs", "args": [52, 68, 53, 68] },
    { "command": "DrawAbs", "args": [52, 67, 53, 67] },
    { "command": "DrawAbs", "args": [52, 66, 53, 66] },
    { "command": "DrawAbs", "args": [52, 65, 53, 65] },
    { "command": "DrawAbs", "args": [52, 64, 53, 64] },
    { "command": "DrawAbs", "args": [52, 63, 53, 63] },
    { "command": "DrawAbs", "args": [52, 62, 53, 62] },
    { "command": "DrawAbs", "args": [52, 61, 53, 61] },
    { "command": "DrawAbs", "args": [52, 60, 53, 60] },
    { "command": "DrawAbs", "args": [52, 59, 53, 59] },
    { "command": "DrawAbs", "args": [52, 58, 53, 58] },
    { "command": "DrawAbs", "args": [53, 58, 54, 58] },
    { "command": "DrawAbs", "args": [53, 59, 54, 59] },
    { "command": "DrawAbs", "args": [54, 59, 55, 59] },
    { "command": "DrawAbs", "args": [55, 59, 56, 59] },
    { "command": "DrawAbs", "args": [56, 59, 57, 59] },
    { "command": "DrawAbs", "args": [56, 60, 57, 60] },
    { "command": "DrawAbs", "args": [56, 61, 57, 61] },
    { "command": "DrawAbs", "args": [56, 62, 57, 62] },
    { "command": "DrawAbs", "args": [56, 63, 57, 63] },
    { "command": "DrawAbs", "args": [56, 64, 57, 64] },
    { "command": "DrawAbs", "args": [56, 65, 57, 65] },
    { "command": "DrawAbs", "args": [56, 66, 57, 66] },
    { "command": "DrawAbs", "args": [55, 66, 56, 66] },
    { "command": "DrawAbs", "args": [55, 67, 56, 67] },
    { "command": "DrawAbs", "args": [55, 68, 56, 68] },
    { "command": "DrawAbs", "args": [56, 68, 57, 68] },
    { "command": "DrawAbs", "args": [56, 69, 57, 69] },
    { "command": "DrawAbs", "args": [56, 70, 57, 70] },
    { "command": "DrawAbs", "args": [56, 71, 57, 71] },
    { "command": "DrawAbs", "args": [56, 72, 57, 72] },
    { "command": "DrawAbs", "args": [57, 72, 58, 72] },
    { "command": "DrawAbs", "args": [57, 73, 58, 73] },
    { "command": "DrawAbs", "args": [58, 73, 59, 73] },
    { "command": "DrawAbs", "args": [58, 74, 59, 74] },
    { "command": "DrawAbs", "args": [59, 74, 60, 74] },
    { "command": "DrawAbs", "args": [59, 73, 60, 73] },
    { "command": "DrawAbs", "args": [60, 73, 61, 73] },
    { "command": "DrawAbs", "args": [61, 73, 62, 73] },
    { "command": "DrawAbs", "args": [62, 73, 63, 73] },
    { "command": "DrawAbs", "args": [63, 73, 64, 73] },
    { "command": "DrawAbs", "args": [64, 73, 65, 73] },
    { "command": "DrawAbs", "args": [64, 74, 65, 74] },
    { "command": "DrawAbs", "args": [65, 74, 66, 74] },
    { "command": "DrawAbs", "args": [66, 74, 67, 74] },
    { "command": "DrawAbs", "args": [67, 74, 68, 74] },
    { "command": "DrawAbs", "args": [67, 73, 68, 73] },
    { "command": "DrawAbs", "args": [67, 72, 68, 72] },
    { "command": "DrawAbs", "args": [67, 71, 68, 71] },
    { "command": "DrawAbs", "args": [66, 70, 67, 70] },
    { "command": "DrawAbs", "args": [66, 69, 67, 69] },
    { "command": "DrawAbs", "args": [66, 68, 67, 68] },
    { "command": "DrawAbs", "args": [66, 67, 67, 67] },
    { "command": "DrawAbs", "args": [66, 66, 67, 66] },
    { "command": "DrawAbs", "args": [66, 65, 67, 65] },
    { "command": "DrawAbs", "args": [65, 64, 66, 64] },
    { "command": "DrawAbs", "args": [65, 63, 66, 63] },
    { "command": "DrawAbs", "args": [65, 62, 66, 62] },
    { "command": "DrawAbs", "args": [65, 61, 66, 61] },
    { "command": "DrawAbs", "args": [65, 60, 66, 60] },
    { "command": "DrawAbs", "args": [65, 59, 66, 59] },
    { "command": "DrawAbs", "args": [64, 59, 65, 59] },
    { "command": "DrawAbs", "args": [64, 58, 65, 58] },
    { "command": "DrawAbs", "args": [64, 57, 65, 57] },
    { "command": "DrawAbs", "args": [64, 56, 65, 56] },
    { "command": "DrawAbs", "args": [64, 55, 65, 55] },
    { "command": "DrawAbs", "args": [64, 54, 65, 54] },
    { "command": "DrawAbs", "args": [64, 53, 65, 53] },
    { "command": "DrawAbs", "args": [63, 52, 64, 52] },
    { "command": "DrawAbs", "args": [63, 51, 64, 51] },
    { "command": "DrawAbs", "args": [63, 50, 64, 50] },
    { "command": "DrawAbs", "args": [63, 49, 64, 49] },
    { "command": "DrawAbs", "args": [63, 48, 64, 48] },
    { "command": "DrawAbs", "args": [62, 48, 63, 48] },
    { "command": "DrawAbs", "args": [62, 47, 63, 47] },
    { "command": "DrawAbs", "args": [62, 46, 63, 46] },
    { "command": "DrawAbs", "args": [62, 45, 63, 45] },
    { "command": "DrawAbs", "args": [62, 44, 63, 44] },
    { "command": "DrawAbs", "args": [62, 43, 63, 43] },
    { "command": "DrawAbs", "args": [62, 42, 63, 42] },
    { "command": "DrawAbs", "args": [62, 41, 63, 41] },
    { "command": "DrawAbs", "args": [62, 40, 63, 40] },
    { "command": "DrawAbs", "args": [61, 40, 62, 40] },
    { "command": "DrawAbs", "args": [61, 39, 62, 39] },
    { "command": "DrawAbs", "args": [61, 38, 62, 38] },
    { "command": "DrawAbs", "args": [61, 37, 62, 37] },
    { "command": "DrawAbs", "args": [61, 36, 62, 36] },
    { "command": "DrawAbs", "args": [61, 35, 62, 35] },
    { "command": "DrawAbs", "args": [61, 34, 62, 34] },
    { "command": "DrawAbs", "args": [61, 33, 62, 33] },
    { "command": "DrawAbs", "args": [61, 32, 62, 32] },
    { "command": "DrawAbs", "args": [61, 31, 62, 31] },
    { "command": "DrawAbs", "args": [61, 30, 62, 30] },
    { "command": "DrawAbs", "args": [61, 29, 62, 29] },
    { "command": "DrawAbs", "args": [61, 28, 62, 28] },
    { "command": "DrawAbs", "args": [60, 27, 61, 27] },
    { "command": "DrawAbs", "args": [60, 26, 61, 26] },
    { "command": "DrawAbs", "args": [60, 25, 61, 25] },
    { "command": "DrawAbs", "args": [60, 24, 61, 24] },
    { "command": "DrawAbs", "args": [60, 23, 61, 23] },
    { "command": "DrawAbs", "args": [59, 23, 60, 23] },
    { "command": "DrawAbs", "args": [59, 22, 60, 22] },
    { "command": "DrawAbs", "args": [59, 21, 60, 21] },
    { "command": "DrawAbs", "args": [58, 21, 59, 21] },
    { "command": "DrawAbs", "args": [58, 20, 59, 20] },
    { "command": "DrawAbs", "args": [58, 19, 59, 19] },
    { "command": "DrawAbs", "args": [57, 19, 58, 19] },
    { "command": "DrawAbs", "args": [56, 19, 57, 19] },
    { "command": "DrawAbs", "args": [56, 18, 57, 18] },
    { "command": "DrawAbs", "args": [55, 18, 56, 18] },
    { "command": "DrawAbs", "args": [54, 18, 55, 18] },
    { "command": "DrawAbs", "args": [53, 18, 54, 18] },
    { "command": "DrawAbs", "args": [53, 17, 54, 17] },
    { "command": "DrawAbs", "args": [52, 17, 53, 17] },
    { "command": "DrawAbs", "args": [51, 17, 52, 17] },
    { "command": "DrawAbs", "args": [50, 17, 51, 17] },
    { "command": "DrawAbs", "args": [50, 16, 51, 16] },
    { "command": "DrawAbs", "args": [49, 16, 50, 16] },
    { "command": "DrawAbs", "args": [48, 16, 49, 16] },
    { "command": "DrawAbs", "args": [48, 17, 49, 17] },
    { "command": "DrawAbs", "args": [48, 18, 49, 18] },
    { "command": "DrawAbs", "args": [48, 19, 49, 19] },
    { "command": "DrawAbs", "args": [48, 20, 49, 20] },
    { "command": "DrawAbs", "args": [48, 21, 49, 21] },
    { "command": "DrawAbs", "args": [47, 21, 48, 21] },
    { "command": "DrawAbs", "args": [47, 22, 48, 22] },
    { "command": "DrawAbs", "args": [47, 23, 48, 23] },
    { "command": "DrawAbs", "args": [47, 24, 48, 24] },
    { "command": "DrawAbs", "args": [47, 25, 48, 25] },
    { "command": "DrawAbs", "args": [47, 26, 48, 26] },
    { "command": "DrawAbs", "args": [47, 27, 48, 27] },
    { "command": "DrawAbs", "args": [53, 29, 54, 29] },
    { "command": "DrawAbs", "args": [53, 30, 54, 30] },
    { "command": "DrawAbs", "args": [53, 31, 54, 31] },
    { "command": "DrawAbs", "args": [52, 31, 53, 31] },
    { "command": "DrawAbs", "args": [52, 32, 53, 32] },
    { "command": "DrawAbs", "args": [52, 33, 53, 33] },
    { "command": "DrawAbs", "args": [52, 34, 53, 34] },
    { "command": "DrawAbs", "args": [51, 34, 52, 34] },
    { "command": "DrawAbs", "args": [51, 35, 52, 35] },
    { "command": "DrawAbs", "args": [51, 36, 52, 36] },
    { "command": "DrawAbs", "args": [51, 37, 52, 37] },
    { "command": "DrawAbs", "args": [51, 38, 52, 38] },
    { "command": "DrawAbs", "args": [50, 38, 51, 38] },
    { "command": "DrawAbs", "args": [50, 39, 51, 39] },
    { "command": "DrawAbs", "args": [50, 40, 51, 40] },
    { "command": "DrawAbs", "args": [50, 41, 51, 41] },
    { "command": "DrawAbs", "args": [51, 41, 52, 41] },
    { "command": "DrawAbs", "args": [52, 41, 53, 41] },
    { "command": "DrawAbs", "args": [52, 42, 53, 42] },
    { "command": "DrawAbs", "args": [53, 42, 54, 42] },
    { "command": "DrawAbs", "args": [54, 42, 55, 42] },
    { "command": "DrawAbs", "args": [55, 42, 56, 42] },
    { "command": "DrawAbs", "args": [55, 41, 56, 41] },
    { "command": "DrawAbs", "args": [55, 40, 56, 40] },
    { "command": "DrawAbs", "args": [55, 39, 56, 39] },
    { "command": "DrawAbs", "args": [55, 38, 56, 38] },
    { "command": "DrawAbs", "args": [55, 37, 56, 37] },
    { "command": "DrawAbs", "args": [55, 36, 56, 36] },
    { "command": "DrawAbs", "args": [55, 35, 56, 35] },
    { "command": "DrawAbs", "args": [55, 34, 56, 34] },
    { "command": "DrawAbs", "args": [54, 34, 55, 34] },
    { "command": "DrawAbs", "args": [54, 33, 55, 33] },
    { "command": "DrawAbs", "args": [54, 32, 55, 32] },
    { "command": "DrawAbs", "args": [54, 31, 55, 31] },
    { "command": "DrawAbs", "args": [74, 22, 75, 22] },
    { "command": "DrawAbs", "args": [74, 23, 75, 23] },
    { "command": "DrawAbs", "args": [73, 23, 74, 23] },
    { "command": "DrawAbs", "args": [73, 24, 74, 24] },
    { "command": "DrawAbs", "args": [73, 25, 74, 25] },
    { "command": "DrawAbs", "args": [73, 26, 74, 26] },
    { "command": "DrawAbs", "args": [73, 27, 74, 27] },
    { "command": "DrawAbs", "args": [73, 28, 74, 28] },
    { "command": "DrawAbs", "args": [73, 29, 74, 29] },
    { "command": "DrawAbs", "args": [73, 30, 74, 30] },
    { "command": "DrawAbs", "args": [72, 30, 73, 30] },
    { "command": "DrawAbs", "args": [72, 31, 73, 31] },
    { "command": "DrawAbs", "args": [72, 32, 73, 32] },
    { "command": "DrawAbs", "args": [72, 33, 73, 33] },
    { "command": "DrawAbs", "args": [72, 34, 73, 34] },
    { "command": "DrawAbs", "args": [72, 35, 73, 35] },
    { "command": "DrawAbs", "args": [72, 36, 73, 36] },
    { "command": "DrawAbs", "args": [72, 37, 73, 37] },
    { "command": "DrawAbs", "args": [72, 38, 73, 38] },
    { "command": "DrawAbs", "args": [72, 39, 73, 39] },
    { "command": "DrawAbs", "args": [72, 40, 73, 40] },
    { "command": "DrawAbs", "args": [72, 41, 73, 41] },
    { "command": "DrawAbs", "args": [72, 42, 73, 42] },
    { "command": "DrawAbs", "args": [72, 43, 73, 43] },
    { "command": "DrawAbs", "args": [72, 44, 73, 44] },
    { "command": "DrawAbs", "args": [73, 45, 74, 45] },
    { "command": "DrawAbs", "args": [73, 46, 74, 46] },
    { "command": "DrawAbs", "args": [73, 47, 74, 47] },
    { "command": "DrawAbs", "args": [73, 48, 74, 48] },
    { "command": "DrawAbs", "args": [73, 49, 74, 49] },
    { "command": "DrawAbs", "args": [73, 50, 74, 50] },
    { "command": "DrawAbs", "args": [73, 51, 74, 51] },
    { "command": "DrawAbs", "args": [73, 52, 74, 52] },
    { "command": "DrawAbs", "args": [73, 53, 74, 53] },
    { "command": "DrawAbs", "args": [73, 54, 74, 54] },
    { "command": "DrawAbs", "args": [73, 55, 74, 55] },
    { "command": "DrawAbs", "args": [73, 56, 74, 56] },
    { "command": "DrawAbs", "args": [73, 57, 74, 57] },
    { "command": "DrawAbs", "args": [73, 58, 74, 58] },
    { "command": "DrawAbs", "args": [73, 59, 74, 59] },
    { "command": "DrawAbs", "args": [73, 60, 74, 60] },
    { "command": "DrawAbs", "args": [73, 61, 74, 61] },
    { "command": "DrawAbs", "args": [73, 62, 74, 62] },
    { "command": "DrawAbs", "args": [73, 63, 74, 63] },
    { "command": "DrawAbs", "args": [74, 63, 75, 63] },
    { "command": "DrawAbs", "args": [74, 64, 75, 64] },
    { "command": "DrawAbs", "args": [74, 65, 75, 65] },
    { "command": "DrawAbs", "args": [74, 66, 75, 66] },
    { "command": "DrawAbs", "args": [74, 67, 75, 67] },
    { "command": "DrawAbs", "args": [74, 68, 75, 68] },
    { "command": "DrawAbs", "args": [74, 69, 75, 69] },
    { "command": "DrawAbs", "args": [74, 70, 75, 70] },
    { "command": "DrawAbs", "args": [74, 71, 75, 71] },
    { "command": "DrawAbs", "args": [74, 72, 75, 72] },
    { "command": "DrawAbs", "args": [74, 73, 75, 73] },
    { "command": "DrawAbs", "args": [74, 74, 75, 74] },
    { "command": "DrawAbs", "args": [74, 75, 75, 75] },
    { "command": "DrawAbs", "args": [75, 75, 76, 75] },
    { "command": "DrawAbs", "args": [76, 75, 77, 75] },
    { "command": "DrawAbs", "args": [77, 75, 78, 75] },
    { "command": "DrawAbs", "args": [77, 76, 78, 76] },
    { "command": "DrawAbs", "args": [78, 76, 79, 76] },
    { "command": "DrawAbs", "args": [79, 76, 80, 76] },
    { "command": "DrawAbs", "args": [80, 76, 81, 76] },
    { "command": "DrawAbs", "args": [80, 77, 81, 77] },
    { "command": "DrawAbs", "args": [81, 77, 82, 77] },
    { "command": "DrawAbs", "args": [82, 77, 83, 77] },
    { "command": "DrawAbs", "args": [83, 77, 84, 77] },
    { "command": "DrawAbs", "args": [84, 77, 85, 77] },
    { "command": "DrawAbs", "args": [85, 77, 86, 77] },
    { "command": "DrawAbs", "args": [86, 77, 87, 77] },
    { "command": "DrawAbs", "args": [86, 76, 87, 76] },
    { "command": "DrawAbs", "args": [87, 76, 88, 76] },
    { "command": "DrawAbs", "args": [87, 75, 88, 75] },
    { "command": "DrawAbs", "args": [88, 75, 89, 75] },
    { "command": "DrawAbs", "args": [88, 74, 89, 74] },
    { "command": "DrawAbs", "args": [89, 74, 90, 74] },
    { "command": "DrawAbs", "args": [89, 73, 90, 73] },
    { "command": "DrawAbs", "args": [89, 72, 90, 72] },
    { "command": "DrawAbs", "args": [89, 71, 90, 71] },
    { "command": "DrawAbs", "args": [89, 70, 90, 70] },
    { "command": "DrawAbs", "args": [89, 69, 90, 69] },
    { "command": "DrawAbs", "args": [89, 68, 90, 68] },
    { "command": "DrawAbs", "args": [89, 67, 90, 67] },
    { "command": "DrawAbs", "args": [89, 66, 90, 66] },
    { "command": "DrawAbs", "args": [89, 65, 90, 65] },
    { "command": "DrawAbs", "args": [90, 65, 91, 65] },
    { "command": "DrawAbs", "args": [90, 64, 91, 64] },
    { "command": "DrawAbs", "args": [91, 64, 92, 64] },
    { "command": "DrawAbs", "args": [91, 65, 92, 65] },
    { "command": "DrawAbs", "args": [91, 66, 92, 66] },
    { "command": "DrawAbs", "args": [91, 67, 92, 67] },
    { "command": "DrawAbs", "args": [91, 68, 92, 68] },
    { "command": "DrawAbs", "args": [90, 68, 91, 68] },
    { "command": "DrawAbs", "args": [90, 69, 91, 69] },
    { "command": "DrawAbs", "args": [90, 70, 91, 70] },
    { "command": "DrawAbs", "args": [91, 71, 92, 71] },
    { "command": "DrawAbs", "args": [91, 72, 92, 72] },
    { "command": "DrawAbs", "args": [92, 72, 93, 72] },
    { "command": "DrawAbs", "args": [92, 73, 93, 73] },
    { "command": "DrawAbs", "args": [93, 73, 94, 73] },
    { "command": "DrawAbs", "args": [93, 74, 94, 74] },
    { "command": "DrawAbs", "args": [94, 74, 95, 74] },
    { "command": "DrawAbs", "args": [94, 75, 95, 75] },
    { "command": "DrawAbs", "args": [95, 75, 96, 75] },
    { "command": "DrawAbs", "args": [95, 76, 96, 76] },
    { "command": "DrawAbs", "args": [96, 76, 97, 76] },
    { "command": "DrawAbs", "args": [96, 77, 97, 77] },
    { "command": "DrawAbs", "args": [97, 77, 98, 77] },
    { "command": "DrawAbs", "args": [98, 77, 99, 77] },
    { "command": "DrawAbs", "args": [99, 77, 100, 77] },
    { "command": "DrawAbs", "args": [100, 77, 101, 77] },
    { "command": "DrawAbs", "args": [101, 77, 102, 77] },
    { "command": "DrawAbs", "args": [102, 77, 103, 77] },
    { "command": "DrawAbs", "args": [102, 76, 103, 76] },
    { "command": "DrawAbs", "args": [102, 75, 103, 75] },
    { "command": "DrawAbs", "args": [102, 74, 103, 74] },
    { "command": "DrawAbs", "args": [102, 73, 103, 73] },
    { "command": "DrawAbs", "args": [102, 72, 103, 72] },
    { "command": "DrawAbs", "args": [102, 71, 103, 71] },
    { "command": "DrawAbs", "args": [101, 71, 102, 71] },
    { "command": "DrawAbs", "args": [101, 70, 102, 70] },
    { "command": "DrawAbs", "args": [100, 70, 101, 70] },
    { "command": "DrawAbs", "args": [100, 69, 101, 69] },
    { "command": "DrawAbs", "args": [100, 68, 101, 68] },
    { "command": "DrawAbs", "args": [100, 67, 101, 67] },
    { "command": "DrawAbs", "args": [99, 66, 100, 66] },
    { "command": "DrawAbs", "args": [99, 65, 100, 65] },
    { "command": "DrawAbs", "args": [99, 64, 100, 64] },
    { "command": "DrawAbs", "args": [99, 63, 100, 63] },
    { "command": "DrawAbs", "args": [99, 62, 100, 62] },
    { "command": "DrawAbs", "args": [99, 61, 100, 61] },
    { "command": "DrawAbs", "args": [100, 61, 101, 61] },
    { "command": "DrawAbs", "args": [100, 60, 101, 60] },
    { "command": "DrawAbs", "args": [100, 59, 101, 59] },
    { "command": "DrawAbs", "args": [100, 58, 101, 58] },
    { "command": "DrawAbs", "args": [100, 57, 101, 57] },
    { "command": "DrawAbs", "args": [100, 56, 101, 56] },
    { "command": "DrawAbs", "args": [99, 56, 100, 56] },
    { "command": "DrawAbs", "args": [99, 55, 100, 55] },
    { "command": "DrawAbs", "args": [99, 54, 100, 54] },
    { "command": "DrawAbs", "args": [99, 53, 100, 53] },
    { "command": "DrawAbs", "args": [98, 52, 99, 52] },
    { "command": "DrawAbs", "args": [98, 51, 99, 51] },
    { "command": "DrawAbs", "args": [98, 50, 99, 50] },
    { "command": "DrawAbs", "args": [97, 50, 98, 50] },
    { "command": "DrawAbs", "args": [97, 49, 98, 49] },
    { "command": "DrawAbs", "args": [97, 48, 98, 48] },
    { "command": "DrawAbs", "args": [96, 48, 97, 48] },
    { "command": "DrawAbs", "args": [96, 47, 97, 47] },
    { "command": "DrawAbs", "args": [95, 47, 96, 47] },
    { "command": "DrawAbs", "args": [95, 46, 96, 46] },
    { "command": "DrawAbs", "args": [94, 46, 95, 46] },
    { "command": "DrawAbs", "args": [93, 46, 94, 46] },
    { "command": "DrawAbs", "args": [92, 46, 93, 46] },
    { "command": "DrawAbs", "args": [92, 45, 93, 45] },
    { "command": "DrawAbs", "args": [91, 45, 92, 45] },
    { "command": "DrawAbs", "args": [90, 45, 91, 45] },
    { "command": "DrawAbs", "args": [89, 45, 90, 45] },
    { "command": "DrawAbs", "args": [88, 45, 89, 45] },
    { "command": "DrawAbs", "args": [88, 44, 89, 44] },
    { "command": "DrawAbs", "args": [87, 44, 88, 44] },
    { "command": "DrawAbs", "args": [86, 44, 87, 44] },
    { "command": "DrawAbs", "args": [85, 45, 86, 45] },
    { "command": "DrawAbs", "args": [85, 46, 86, 46] },
    { "command": "DrawAbs", "args": [85, 47, 86, 47] },
    { "command": "DrawAbs", "args": [85, 48, 86, 48] },
    { "command": "DrawAbs", "args": [85, 49, 86, 49] },
    { "command": "DrawAbs", "args": [85, 50, 86, 50] },
    { "command": "DrawAbs", "args": [85, 51, 86, 51] },
    { "command": "DrawAbs", "args": [85, 52, 86, 52] },
    { "command": "DrawAbs", "args": [85, 53, 86, 53] },
    { "command": "DrawAbs", "args": [85, 54, 86, 54] },
    { "command": "DrawAbs", "args": [85, 55, 86, 55] },
    { "command": "DrawAbs", "args": [85, 56, 86, 56] },
    { "command": "DrawAbs", "args": [85, 57, 86, 57] },
    { "command": "DrawAbs", "args": [86, 57, 87, 57] },
    { "command": "DrawAbs", "args": [86, 58, 87, 58] },
    { "command": "DrawAbs", "args": [87, 58, 88, 58] },
    { "command": "DrawAbs", "args": [88, 58, 89, 58] },
    { "command": "DrawAbs", "args": [89, 58, 90, 58] },
    { "command": "DrawAbs", "args": [89, 59, 90, 59] },
    { "command": "DrawAbs", "args": [90, 59, 91, 59] },
    { "command": "DrawAbs", "args": [89, 59, 90, 59] },
    { "command": "DrawAbs", "args": [89, 58, 90, 58] },
    { "command": "DrawAbs", "args": [88, 58, 89, 58] },
    { "command": "DrawAbs", "args": [87, 59, 88, 59] },
    { "command": "DrawAbs", "args": [87, 60, 88, 60] },
    { "command": "DrawAbs", "args": [87, 61, 88, 61] },
    { "command": "DrawAbs", "args": [86, 61, 87, 61] },
    { "command": "DrawAbs", "args": [86, 62, 87, 62] },
    { "command": "DrawAbs", "args": [86, 63, 87, 63] },
    { "command": "DrawAbs", "args": [85, 63, 86, 63] },
    { "command": "DrawAbs", "args": [84, 63, 85, 63] },
    { "command": "DrawAbs", "args": [84, 64, 85, 64] },
    { "command": "DrawAbs", "args": [83, 64, 84, 64] },
    { "command": "DrawAbs", "args": [83, 63, 84, 63] },
    { "command": "DrawAbs", "args": [83, 62, 84, 62] },
    { "command": "DrawAbs", "args": [83, 61, 84, 61] },
    { "command": "DrawAbs", "args": [83, 60, 84, 60] },
    { "command": "DrawAbs", "args": [82, 60, 83, 60] },
    { "command": "DrawAbs", "args": [82, 59, 83, 59] },
    { "command": "DrawAbs", "args": [82, 58, 83, 58] },
    { "command": "DrawAbs", "args": [82, 57, 83, 57] },
    { "command": "DrawAbs", "args": [83, 57, 84, 57] },
    { "command": "DrawAbs", "args": [83, 56, 84, 56] },
    { "command": "DrawAbs", "args": [83, 55, 84, 55] },
    { "command": "DrawAbs", "args": [83, 54, 84, 54] },
    { "command": "DrawAbs", "args": [82, 54, 83, 54] },
    { "command": "DrawAbs", "args": [82, 53, 83, 53] },
    { "command": "DrawAbs", "args": [82, 52, 83, 52] },
    { "command": "DrawAbs", "args": [82, 51, 83, 51] },
    { "command": "DrawAbs", "args": [82, 50, 83, 50] },
    { "command": "DrawAbs", "args": [82, 49, 83, 49] },
    { "command": "DrawAbs", "args": [81, 49, 82, 49] },
    { "command": "DrawAbs", "args": [81, 48, 82, 48] },
    { "command": "DrawAbs", "args": [81, 47, 82, 47] },
    { "command": "DrawAbs", "args": [81, 46, 82, 46] },
    { "command": "DrawAbs", "args": [81, 45, 82, 45] },
    { "command": "DrawAbs", "args": [81, 44, 82, 44] },
    { "command": "DrawAbs", "args": [81, 43, 82, 43] },
    { "command": "DrawAbs", "args": [81, 42, 82, 42] },
    { "command": "DrawAbs", "args": [80, 42, 81, 42] },
    { "command": "DrawAbs", "args": [80, 41, 81, 41] },
    { "command": "DrawAbs", "args": [80, 40, 81, 40] },
    { "command": "DrawAbs", "args": [80, 39, 81, 39] },
    { "command": "DrawAbs", "args": [80, 38, 81, 38] },
    { "command": "DrawAbs", "args": [80, 37, 81, 37] },
    { "command": "DrawAbs", "args": [80, 36, 81, 36] },
    { "command": "DrawAbs", "args": [80, 35, 81, 35] },
    { "command": "DrawAbs", "args": [80, 34, 81, 34] },
    { "command": "DrawAbs", "args": [80, 33, 81, 33] },
    { "command": "DrawAbs", "args": [80, 32, 81, 32] },
    { "command": "DrawAbs", "args": [80, 31, 81, 31] },
    { "command": "DrawAbs", "args": [80, 30, 81, 30] },
    { "command": "DrawAbs", "args": [80, 29, 81, 29] },
    { "command": "DrawAbs", "args": [81, 29, 82, 29] },
    { "command": "DrawAbs", "args": [81, 28, 82, 28] },
    { "command": "DrawAbs", "args": [82, 28, 83, 28] },
    { "command": "DrawAbs", "args": [83, 28, 84, 28] },
    { "command": "DrawAbs", "args": [84, 28, 85, 28] },
    { "command": "DrawAbs", "args": [84, 29, 85, 29] },
    { "command": "DrawAbs", "args": [84, 30, 85, 30] },
    { "command": "DrawAbs", "args": [85, 31, 86, 31] },
    { "command": "DrawAbs", "args": [85, 32, 86, 32] },
    { "command": "DrawAbs", "args": [85, 33, 86, 33] },
    { "command": "DrawAbs", "args": [85, 34, 86, 34] },
    { "command": "DrawAbs", "args": [85, 35, 86, 35] },
    { "command": "DrawAbs", "args": [86, 35, 87, 35] },
    { "command": "DrawAbs", "args": [86, 36, 87, 36] },
    { "command": "DrawAbs", "args": [86, 37, 87, 37] },
    { "command": "DrawAbs", "args": [86, 38, 87, 38] },
    { "command": "DrawAbs", "args": [86, 39, 87, 39] },
    { "command": "DrawAbs", "args": [86, 40, 87, 40] },
    { "command": "DrawAbs", "args": [87, 40, 88, 40] },
    { "command": "DrawAbs", "args": [88, 41, 89, 41] },
    { "command": "DrawAbs", "args": [89, 41, 90, 41] },
    { "command": "DrawAbs", "args": [90, 41, 91, 41] },
    { "command": "DrawAbs", "args": [91, 41, 92, 41] },
    { "command": "DrawAbs", "args": [92, 41, 93, 41] },
    { "command": "DrawAbs", "args": [92, 40, 93, 40] },
    { "command": "DrawAbs", "args": [93, 40, 94, 40] },
    { "command": "DrawAbs", "args": [94, 40, 95, 40] },
    { "command": "DrawAbs", "args": [94, 39, 95, 39] },
    { "command": "DrawAbs", "args": [94, 38, 95, 38] },
    { "command": "DrawAbs", "args": [94, 37, 95, 37] },
    { "command": "DrawAbs", "args": [94, 36, 95, 36] },
    { "command": "DrawAbs", "args": [93, 36, 94, 36] },
    { "command": "DrawAbs", "args": [93, 35, 94, 35] },
    { "command": "DrawAbs", "args": [93, 34, 94, 34] },
    { "command": "DrawAbs", "args": [93, 33, 94, 33] },
    { "command": "DrawAbs", "args": [92, 33, 93, 33] },
    { "command": "DrawAbs", "args": [92, 32, 93, 32] },
    { "command": "DrawAbs", "args": [92, 31, 93, 31] },
    { "command": "DrawAbs", "args": [92, 30, 93, 30] },
    { "command": "DrawAbs", "args": [91, 30, 92, 30] },
    { "command": "DrawAbs", "args": [91, 29, 92, 29] },
    { "command": "DrawAbs", "args": [91, 28, 92, 28] },
    { "command": "DrawAbs", "args": [91, 27, 92, 27] },
    { "command": "DrawAbs", "args": [90, 27, 91, 27] },
    { "command": "DrawAbs", "args": [90, 26, 91, 26] },
    { "command": "DrawAbs", "args": [90, 25, 91, 25] },
    { "command": "DrawAbs", "args": [90, 24, 91, 24] },
    { "command": "DrawAbs", "args": [89, 24, 90, 24] },
    { "command": "DrawAbs", "args": [89, 23, 90, 23] },
    { "command": "DrawAbs", "args": [89, 22, 90, 22] },
    { "command": "DrawAbs", "args": [89, 21, 90, 21] },
    { "command": "DrawAbs", "args": [88, 21, 89, 21] },
    { "command": "DrawAbs", "args": [88, 20, 89, 20] },
    { "command": "DrawAbs", "args": [88, 19, 89, 19] },
    { "command": "DrawAbs", "args": [87, 19, 88, 19] },
    { "command": "DrawAbs", "args": [87, 18, 88, 18] },
    { "command": "DrawAbs", "args": [87, 17, 88, 17] },
    { "command": "DrawAbs", "args": [86, 17, 87, 17] },
    { "command": "DrawAbs", "args": [86, 16, 87, 16] },
    { "command": "DrawAbs", "args": [85, 16, 86, 16] },
    { "command": "DrawAbs", "args": [85, 15, 86, 15] },
    { "command": "DrawAbs", "args": [84, 15, 85, 15] },
    { "command": "DrawAbs", "args": [83, 15, 84, 15] },
    { "command": "DrawAbs", "args": [83, 16, 84, 16] },
    { "command": "DrawAbs", "args": [82, 16, 83, 16] },
    { "command": "DrawAbs", "args": [81, 16, 82, 16] },
    { "command": "DrawAbs", "args": [80, 16, 81, 16] },
    { "command": "DrawAbs", "args": [80, 15, 81, 15] },
    { "command": "DrawAbs", "args": [79, 15, 80, 15] },
    { "command": "DrawAbs", "args": [78, 14, 79, 14] },
    { "command": "DrawAbs", "args": [77, 14, 78, 14] },
    { "command": "DrawAbs", "args": [77, 15, 78, 15] },
    { "command": "DrawAbs", "args": [76, 15, 77, 15] },
    { "command": "DrawAbs", "args": [76, 16, 77, 16] },
    { "command": "DrawAbs", "args": [76, 17, 77, 17] },
    { "command": "DrawAbs", "args": [75, 17, 76, 17] },
    { "command": "DrawAbs", "args": [75, 18, 76, 18] },
    { "command": "DrawAbs", "args": [75, 19, 76, 19] },
    { "command": "DrawAbs", "args": [75, 20, 76, 20] },
    { "command": "DrawAbs", "args": [75, 21, 76, 21] },
    { "command": "DrawAbs", "args": [75, 22, 76, 22] },
    { "command": "PicSetColor", "args": [9] },
    { "command": "DrawAbs", "args": [107, 79, 108, 79] },
    { "command": "DrawAbs", "args": [108, 79, 109, 79] },
    { "command": "DrawAbs", "args": [108, 78, 109, 78] },
    { "command": "DrawAbs", "args": [109, 78, 110, 78] },
    { "command": "DrawAbs", "args": [110, 78, 111, 78] },
    { "command": "DrawAbs", "args": [110, 77, 111, 77] },
    { "command": "DrawAbs", "args": [111, 77, 112, 77] },
    { "command": "DrawAbs", "args": [112, 77, 113, 77] },
    { "command": "DrawAbs", "args": [113, 77, 114, 77] },
    { "command": "DrawAbs", "args": [114, 77, 115, 77] },
    { "command": "DrawAbs", "args": [115, 77, 116, 77] },
    { "command": "DrawAbs", "args": [116, 77, 117, 77] },
    { "command": "DrawAbs", "args": [117, 77, 118, 77] },
    { "command": "DrawAbs", "args": [118, 77, 119, 77] },
    { "command": "DrawAbs", "args": [119, 77, 120, 77] },
    { "command": "DrawAbs", "args": [120, 77, 121, 77] },
    { "command": "DrawAbs", "args": [120, 78, 121, 78] },
    { "command": "DrawAbs", "args": [121, 78, 122, 78] },
    { "command": "DrawAbs", "args": [122, 78, 123, 78] },
    { "command": "DrawAbs", "args": [123, 78, 124, 78] },
    { "command": "DrawAbs", "args": [124, 78, 125, 78] },
    { "command": "DrawAbs", "args": [125, 78, 126, 78] },
    { "command": "DrawAbs", "args": [126, 78, 127, 78] },
    { "command": "DrawAbs", "args": [127, 78, 128, 78] },
    { "command": "DrawAbs", "args": [128, 77, 129, 77] },
    { "command": "DrawAbs", "args": [129, 77, 130, 77] },
    { "command": "DrawAbs", "args": [129, 76, 130, 76] },
    { "command": "DrawAbs", "args": [129, 75, 130, 75] },
    { "command": "PicSetColor", "args": [9] },
    { "command": "DrawAbs", "args": [108, 78, 109, 78] },
    { "command": "DrawAbs", "args": [108, 77, 109, 77] },
    { "command": "DrawAbs", "args": [108, 76, 109, 76] },
    { "command": "DrawAbs", "args": [107, 76, 108, 76] },
    { "command": "DrawAbs", "args": [107, 77, 108, 77] },
    { "command": "DrawAbs", "args": [106, 77, 107, 77] },
    { "command": "DrawAbs", "args": [107, 78, 108, 78] },
    { "command": "DrawAbs", "args": [107, 77, 108, 77] },
    { "command": "DrawAbs", "args": [106, 77, 107, 77] },
    { "command": "DrawAbs", "args": [106, 76, 107, 76] },
    { "command": "DrawAbs", "args": [106, 75, 107, 75] },
    { "command": "DrawAbs", "args": [106, 74, 107, 74] },
    { "command": "DrawAbs", "args": [106, 73, 107, 73] },
    { "command": "DrawAbs", "args": [106, 72, 107, 72] },
    { "command": "DrawAbs", "args": [106, 71, 107, 71] },
    { "command": "DrawAbs", "args": [106, 70, 107, 70] },
    { "command": "DrawAbs", "args": [106, 69, 107, 69] },
    { "command": "DrawAbs", "args": [106, 68, 107, 68] },
    { "command": "DrawAbs", "args": [105, 68, 106, 68] },
    { "command": "DrawAbs", "args": [105, 67, 106, 67] },
    { "command": "DrawAbs", "args": [105, 66, 106, 66] },
    { "command": "DrawAbs", "args": [105, 65, 106, 65] },
    { "command": "DrawAbs", "args": [105, 64, 106, 64] },
    { "command": "DrawAbs", "args": [105, 63, 106, 63] },
    { "command": "DrawAbs", "args": [106, 63, 107, 63] },
    { "command": "DrawAbs", "args": [107, 63, 108, 63] },
    { "command": "DrawAbs", "args": [108, 63, 109, 63] },
    { "command": "DrawAbs", "args": [109, 63, 110, 63] },
    { "command": "DrawAbs", "args": [110, 63, 111, 63] },
    { "command": "DrawAbs", "args": [111, 63, 112, 63] },
    { "command": "DrawAbs", "args": [129, 76, 130, 76] },
    { "command": "DrawAbs", "args": [129, 75, 130, 75] },
    { "command": "DrawAbs", "args": [129, 74, 130, 74] },
    { "command": "DrawAbs", "args": [129, 73, 130, 73] },
    { "command": "DrawAbs", "args": [129, 72, 130, 72] },
    { "command": "DrawAbs", "args": [128, 72, 129, 72] },
    { "command": "DrawAbs", "args": [128, 71, 129, 71] },
    { "command": "DrawAbs", "args": [128, 70, 129, 70] },
    { "command": "DrawAbs", "args": [128, 69, 129, 69] },
    { "command": "DrawAbs", "args": [128, 68, 129, 68] },
    { "command": "DrawAbs", "args": [128, 67, 129, 67] },
    { "command": "DrawAbs", "args": [128, 66, 129, 66] },
    { "command": "DrawAbs", "args": [128, 65, 129, 65] },
    { "command": "DrawAbs", "args": [128, 64, 129, 64] },
    { "command": "DrawAbs", "args": [127, 64, 128, 64] },
    { "command": "DrawAbs", "args": [127, 63, 128, 63] },
    { "command": "DrawAbs", "args": [127, 62, 128, 62] },
    { "command": "DrawAbs", "args": [126, 62, 127, 62] },
    { "command": "DrawAbs", "args": [125, 62, 126, 62] },
    { "command": "DrawAbs", "args": [125, 63, 126, 63] },
    { "command": "DrawAbs", "args": [124, 63, 125, 63] },
    { "command": "DrawAbs", "args": [124, 64, 125, 64] },
    { "command": "DrawAbs", "args": [123, 64, 124, 64] },
    { "command": "DrawAbs", "args": [123, 63, 124, 63] },
    { "command": "DrawAbs", "args": [122, 63, 123, 63] },
    { "command": "DrawAbs", "args": [121, 63, 122, 63] },
    { "command": "DrawAbs", "args": [122, 63, 123, 63] },
    { "command": "DrawAbs", "args": [112, 63, 113, 63] },
    { "command": "DrawAbs", "args": [112, 62, 113, 62] },
    { "command": "DrawAbs", "args": [112, 61, 113, 61] },
    { "command": "DrawAbs", "args": [111, 61, 112, 61] },
    { "command": "DrawAbs", "args": [111, 60, 112, 60] },
    { "command": "DrawAbs", "args": [111, 59, 112, 59] },
    { "command": "DrawAbs", "args": [110, 59, 111, 59] },
    { "command": "DrawAbs", "args": [110, 58, 111, 58] },
    { "command": "DrawAbs", "args": [110, 57, 111, 57] },
    { "command": "DrawAbs", "args": [110, 56, 111, 56] },
    { "command": "DrawAbs", "args": [110, 55, 111, 55] },
    { "command": "DrawAbs", "args": [110, 54, 111, 54] },
    { "command": "DrawAbs", "args": [109, 54, 110, 54] },
    { "command": "DrawAbs", "args": [109, 53, 110, 53] },
    { "command": "DrawAbs", "args": [109, 52, 110, 52] },
    { "command": "DrawAbs", "args": [109, 51, 110, 51] },
    { "command": "DrawAbs", "args": [109, 50, 110, 50] },
    { "command": "DrawAbs", "args": [109, 49, 110, 49] },
    { "command": "DrawAbs", "args": [109, 48, 110, 48] },
    { "command": "DrawAbs", "args": [108, 48, 109, 48] },
    { "command": "DrawAbs", "args": [108, 47, 109, 47] },
    { "command": "DrawAbs", "args": [108, 46, 109, 46] },
    { "command": "DrawAbs", "args": [108, 45, 109, 45] },
    { "command": "DrawAbs", "args": [108, 44, 109, 44] },
    { "command": "DrawAbs", "args": [108, 43, 109, 43] },
    { "command": "DrawAbs", "args": [108, 42, 109, 42] },
    { "command": "DrawAbs", "args": [108, 41, 109, 41] },
    { "command": "DrawAbs", "args": [107, 41, 108, 41] },
    { "command": "DrawAbs", "args": [107, 40, 108, 40] },
    { "command": "DrawAbs", "args": [107, 39, 108, 39] },
    { "command": "DrawAbs", "args": [107, 38, 108, 38] },
    { "command": "DrawAbs", "args": [107, 37, 108, 37] },
    { "command": "DrawAbs", "args": [106, 37, 107, 37] },
    { "command": "DrawAbs", "args": [106, 36, 107, 36] },
    { "command": "DrawAbs", "args": [106, 35, 107, 35] },
    { "command": "DrawAbs", "args": [106, 34, 107, 34] },
    { "command": "DrawAbs", "args": [106, 33, 107, 33] },
    { "command": "DrawAbs", "args": [106, 32, 107, 32] },
    { "command": "DrawAbs", "args": [106, 31, 107, 31] },
    { "command": "DrawAbs", "args": [105, 31, 106, 31] },
    { "command": "DrawAbs", "args": [105, 30, 106, 30] },
    { "command": "DrawAbs", "args": [105, 29, 106, 29] },
    { "command": "DrawAbs", "args": [104, 29, 105, 29] },
    { "command": "DrawAbs", "args": [104, 28, 105, 28] },
    { "command": "DrawAbs", "args": [103, 28, 104, 28] },
    { "command": "DrawAbs", "args": [102, 28, 103, 28] },
    { "command": "DrawAbs", "args": [101, 28, 102, 28] },
    { "command": "DrawAbs", "args": [100, 28, 101, 28] },
    { "command": "DrawAbs", "args": [99, 28, 100, 28] },
    { "command": "DrawAbs", "args": [98, 28, 99, 28] },
    { "command": "DrawAbs", "args": [97, 28, 98, 28] },
    { "command": "DrawAbs", "args": [98, 28, 99, 28] },
    { "command": "DrawAbs", "args": [98, 27, 99, 27] },
    { "command": "DrawAbs", "args": [98, 26, 99, 26] },
    { "command": "DrawAbs", "args": [98, 25, 99, 25] },
    { "command": "DrawAbs", "args": [98, 24, 99, 24] },
    { "command": "DrawAbs", "args": [98, 23, 99, 23] },
    { "command": "DrawAbs", "args": [97, 23, 98, 23] },
    { "command": "DrawAbs", "args": [97, 22, 98, 22] },
    { "command": "DrawAbs", "args": [97, 21, 98, 21] },
    { "command": "DrawAbs", "args": [97, 20, 98, 20] },
    { "command": "DrawAbs", "args": [96, 20, 97, 20] },
    { "command": "DrawAbs", "args": [95, 19, 96, 19] },
    { "command": "DrawAbs", "args": [95, 18, 96, 18] },
    { "command": "DrawAbs", "args": [95, 17, 96, 17] },
    { "command": "DrawAbs", "args": [94, 17, 95, 17] },
    { "command": "DrawAbs", "args": [95, 17, 96, 17] },
    { "command": "DrawAbs", "args": [95, 16, 96, 16] },
    { "command": "DrawAbs", "args": [95, 15, 96, 15] },
    { "command": "DrawAbs", "args": [96, 15, 97, 15] },
    { "command": "DrawAbs", "args": [97, 15, 98, 15] },
    { "command": "DrawAbs", "args": [97, 14, 98, 14] },
    { "command": "DrawAbs", "args": [98, 14, 99, 14] },
    { "command": "DrawAbs", "args": [99, 14, 100, 14] },
    { "command": "DrawAbs", "args": [100, 14, 101, 14] },
    { "command": "DrawAbs", "args": [101, 14, 102, 14] },
    { "command": "DrawAbs", "args": [102, 14, 103, 14] },
    { "command": "DrawAbs", "args": [103, 15, 104, 15] },
    { "command": "DrawAbs", "args": [104, 15, 105, 15] },
    { "command": "DrawAbs", "args": [105, 15, 106, 15] },
    { "command": "DrawAbs", "args": [106, 15, 107, 15] },
    { "command": "DrawAbs", "args": [107, 15, 108, 15] },
    { "command": "DrawAbs", "args": [108, 15, 109, 15] },
    { "command": "DrawAbs", "args": [109, 15, 110, 15] },
    { "command": "DrawAbs", "args": [110, 14, 111, 14] },
    { "command": "DrawAbs", "args": [111, 14, 112, 14] },
    { "command": "DrawAbs", "args": [112, 13, 113, 13] },
    { "command": "DrawAbs", "args": [113, 13, 114, 13] },
    { "command": "DrawAbs", "args": [114, 13, 115, 13] },
    { "command": "DrawAbs", "args": [115, 13, 116, 13] },
    { "command": "DrawAbs", "args": [116, 13, 117, 13] },
    { "command": "DrawAbs", "args": [117, 13, 118, 13] },
    { "command": "DrawAbs", "args": [117, 14, 118, 14] },
    { "command": "DrawAbs", "args": [118, 14, 119, 14] },
    { "command": "DrawAbs", "args": [119, 14, 120, 14] },
    { "command": "DrawAbs", "args": [119, 13, 120, 13] },
    { "command": "DrawAbs", "args": [120, 13, 121, 13] },
    { "command": "DrawAbs", "args": [121, 13, 122, 13] },
    { "command": "DrawAbs", "args": [122, 13, 123, 13] },
    { "command": "DrawAbs", "args": [123, 13, 124, 13] },
    { "command": "DrawAbs", "args": [124, 13, 125, 13] },
    { "command": "DrawAbs", "args": [125, 13, 126, 13] },
    { "command": "DrawAbs", "args": [126, 13, 127, 13] },
    { "command": "DrawAbs", "args": [126, 14, 127, 14] },
    { "command": "DrawAbs", "args": [126, 15, 127, 15] },
    { "command": "DrawAbs", "args": [126, 16, 127, 16] },
    { "command": "DrawAbs", "args": [126, 17, 127, 17] },
    { "command": "DrawAbs", "args": [126, 18, 127, 18] },
    { "command": "DrawAbs", "args": [126, 19, 127, 19] },
    { "command": "DrawAbs", "args": [127, 19, 128, 19] },
    { "command": "DrawAbs", "args": [127, 20, 128, 20] },
    { "command": "DrawAbs", "args": [127, 21, 128, 21] },
    { "command": "DrawAbs", "args": [127, 22, 128, 22] },
    { "command": "DrawAbs", "args": [127, 23, 128, 23] },
    { "command": "DrawAbs", "args": [127, 24, 128, 24] },
    { "command": "DrawAbs", "args": [127, 25, 128, 25] },
    { "command": "DrawAbs", "args": [126, 25, 127, 25] },
    { "command": "DrawAbs", "args": [125, 25, 126, 25] },
    { "command": "DrawAbs", "args": [124, 25, 125, 25] },
    { "command": "DrawAbs", "args": [124, 26, 125, 26] },
    { "command": "DrawAbs", "args": [123, 26, 124, 26] },
    { "command": "DrawAbs", "args": [122, 26, 123, 26] },
    { "command": "DrawAbs", "args": [121, 26, 122, 26] },
    { "command": "DrawAbs", "args": [121, 27, 122, 27] },
    { "command": "DrawAbs", "args": [120, 27, 121, 27] },
    { "command": "DrawAbs", "args": [119, 27, 120, 27] },
    { "command": "DrawAbs", "args": [118, 27, 119, 27] },
    { "command": "DrawAbs", "args": [117, 28, 118, 28] },
    { "command": "DrawAbs", "args": [116, 28, 117, 28] },
    { "command": "DrawAbs", "args": [116, 29, 117, 29] },
    { "command": "DrawAbs", "args": [117, 29, 118, 29] },
    { "command": "DrawAbs", "args": [117, 30, 118, 30] },
    { "command": "DrawAbs", "args": [117, 31, 118, 31] },
    { "command": "DrawAbs", "args": [117, 32, 118, 32] },
    { "command": "DrawAbs", "args": [118, 32, 119, 32] },
    { "command": "DrawAbs", "args": [118, 33, 119, 33] },
    { "command": "DrawAbs", "args": [118, 34, 119, 34] },
    { "command": "DrawAbs", "args": [118, 35, 119, 35] },
    { "command": "DrawAbs", "args": [118, 36, 119, 36] },
    { "command": "DrawAbs", "args": [118, 37, 119, 37] },
    { "command": "DrawAbs", "args": [119, 37, 120, 37] },
    { "command": "DrawAbs", "args": [119, 38, 120, 38] },
    { "command": "DrawAbs", "args": [119, 39, 120, 39] },
    { "command": "DrawAbs", "args": [119, 40, 120, 40] },
    { "command": "DrawAbs", "args": [119, 41, 120, 41] },
    { "command": "DrawAbs", "args": [120, 41, 121, 41] },
    { "command": "DrawAbs", "args": [120, 42, 121, 42] },
    { "command": "DrawAbs", "args": [120, 43, 121, 43] },
    { "command": "DrawAbs", "args": [120, 44, 121, 44] },
    { "command": "DrawAbs", "args": [121, 45, 122, 45] },
    { "command": "DrawAbs", "args": [121, 46, 122, 46] },
    { "command": "DrawAbs", "args": [121, 47, 122, 47] },
    { "command": "DrawAbs", "args": [121, 48, 122, 48] },
    { "command": "DrawAbs", "args": [121, 49, 122, 49] },
    { "command": "DrawAbs", "args": [121, 50, 122, 50] },
    { "command": "DrawAbs", "args": [122, 50, 123, 50] },
    { "command": "DrawAbs", "args": [122, 51, 123, 51] },
    { "command": "DrawAbs", "args": [122, 52, 123, 52] },
    { "command": "DrawAbs", "args": [122, 53, 123, 53] },
    { "command": "DrawAbs", "args": [122, 54, 123, 54] },
    { "command": "DrawAbs", "args": [122, 55, 123, 55] },
    { "command": "DrawAbs", "args": [123, 55, 124, 55] },
    { "command": "DrawAbs", "args": [123, 56, 124, 56] },
    { "command": "DrawAbs", "args": [123, 57, 124, 57] },
    { "command": "DrawAbs", "args": [123, 58, 124, 58] },
    { "command": "DrawAbs", "args": [123, 59, 124, 59] },
    { "command": "DrawAbs", "args": [123, 60, 124, 60] },
    { "command": "DrawAbs", "args": [123, 61, 124, 61] },
    { "command": "DrawAbs", "args": [123, 62, 124, 62] },
    { "command": "DrawAbs", "args": [122, 62, 123, 62] },
    { "command": "DrawAbs", "args": [122, 63, 123, 63] },
    { "command": "DrawAbs", "args": [122, 64, 123, 64] },
    { "command": "DrawAbs", "args": [122, 65, 123, 65] },
    { "command": "PicSetColor", "args": [10] },
    { "command": "DrawAbs", "args": [98, 73, 99, 73] },
    { "command": "DrawAbs", "args": [98, 72, 99, 72] },
    { "command": "DrawAbs", "args": [97, 72, 98, 72] },
    { "command": "DrawAbs", "args": [97, 71, 98, 71] },
    { "command": "DrawAbs", "args": [96, 71, 97, 71] },
    { "command": "DrawAbs", "args": [96, 70, 97, 70] },
    { "command": "DrawAbs", "args": [95, 70, 96, 70] },
    { "command": "DrawAbs", "args": [95, 69, 96, 69] },
    { "command": "DrawAbs", "args": [94, 69, 95, 69] },
    { "command": "DrawAbs", "args": [93, 69, 94, 69] },
    { "command": "DrawAbs", "args": [93, 70, 94, 70] },
    { "command": "DrawAbs", "args": [92, 70, 93, 70] },
    { "command": "DrawAbs", "args": [92, 71, 93, 71] },
    { "command": "DrawAbs", "args": [91, 71, 92, 71] },
    { "command": "DrawAbs", "args": [91, 72, 92, 72] },
    { "command": "DrawAbs", "args": [91, 73, 92, 73] },
    { "command": "DrawAbs", "args": [91, 74, 92, 74] },
    { "command": "DrawAbs", "args": [92, 74, 93, 74] },
    { "command": "DrawAbs", "args": [92, 75, 93, 75] },
    { "command": "DrawAbs", "args": [93, 75, 94, 75] },
    { "command": "DrawAbs", "args": [93, 76, 94, 76] },
    { "command": "DrawAbs", "args": [94, 76, 95, 76] },
    { "command": "DrawAbs", "args": [95, 76, 96, 76] },
    { "command": "DrawAbs", "args": [95, 77, 96, 77] },
    { "command": "DrawAbs", "args": [96, 77, 97, 77] },
    { "command": "DrawAbs", "args": [96, 78, 97, 78] },
    { "command": "DrawAbs", "args": [96, 79, 97, 79] },
    { "command": "DrawAbs", "args": [97, 79, 98, 79] },
    { "command": "DrawAbs", "args": [97, 80, 98, 80] },
    { "command": "DrawAbs", "args": [97, 81, 98, 81] },
    { "command": "DrawAbs", "args": [97, 82, 98, 82] },
    { "command": "DrawAbs", "args": [97, 83, 98, 83] },
    { "command": "DrawAbs", "args": [97, 84, 98, 84] },
    { "command": "DrawAbs", "args": [97, 85, 98, 85] },
    { "command": "DrawAbs", "args": [97, 86, 98, 86] },
    { "command": "DrawAbs", "args": [97, 87, 98, 87] },
    { "command": "DrawAbs", "args": [96, 87, 97, 87] },
    { "command": "DrawAbs", "args": [96, 88, 97, 88] },
    { "command": "DrawAbs", "args": [95, 88, 96, 88] },
    { "command": "DrawAbs", "args": [95, 89, 96, 89] },
    { "command": "DrawAbs", "args": [94, 89, 95, 89] },
    { "command": "DrawAbs", "args": [94, 90, 95, 90] },
    { "command": "DrawAbs", "args": [93, 90, 94, 90] },
    { "command": "DrawAbs", "args": [93, 89, 94, 89] },
    { "command": "DrawAbs", "args": [92, 89, 93, 89] },
    { "command": "DrawAbs", "args": [92, 88, 93, 88] },
    { "command": "DrawAbs", "args": [92, 87, 93, 87] },
    { "command": "DrawAbs", "args": [91, 86, 92, 86] },
    { "command": "DrawAbs", "args": [91, 85, 92, 85] },
    { "command": "DrawAbs", "args": [91, 84, 92, 84] },
    { "command": "DrawAbs", "args": [91, 83, 92, 83] },
    { "command": "DrawAbs", "args": [90, 83, 91, 83] },
    { "command": "DrawAbs", "args": [90, 82, 91, 82] },
    { "command": "DrawAbs", "args": [90, 81, 91, 81] },
    { "command": "DrawAbs", "args": [101, 89, 102, 89] },
    { "command": "DrawAbs", "args": [102, 89, 103, 89] },
    { "command": "DrawAbs", "args": [102, 88, 103, 88] },
    { "command": "DrawAbs", "args": [103, 88, 104, 88] },
    { "command": "DrawAbs", "args": [103, 87, 104, 87] },
    { "command": "DrawAbs", "args": [103, 86, 104, 86] },
    { "command": "DrawAbs", "args": [103, 85, 104, 85] },
    { "command": "DrawAbs", "args": [103, 84, 104, 84] },
    { "command": "DrawAbs", "args": [103, 83, 104, 83] },
    { "command": "DrawAbs", "args": [103, 82, 104, 82] },
    { "command": "DrawAbs", "args": [102, 82, 103, 82] },
    { "command": "DrawAbs", "args": [102, 81, 103, 81] },
    { "command": "DrawAbs", "args": [102, 80, 103, 80] },
    { "command": "DrawAbs", "args": [102, 79, 103, 79] },
    { "command": "DrawAbs", "args": [102, 78, 103, 78] },
    { "command": "DrawAbs", "args": [102, 77, 103, 77] },
    { "command": "DrawAbs", "args": [102, 76, 103, 76] },
    { "command": "DrawAbs", "args": [102, 75, 103, 75] },
    { "command": "DrawAbs", "args": [102, 74, 103, 74] },
    { "command": "DrawAbs", "args": [102, 73, 103, 73] },
    { "command": "DrawAbs", "args": [101, 73, 102, 73] },
    { "command": "DrawAbs", "args": [101, 72, 102, 72] },
    { "command": "DrawAbs", "args": [101, 71, 102, 71] },
    { "command": "DrawAbs", "args": [101, 70, 102, 70] },
    { "command": "DrawAbs", "args": [101, 69, 102, 69] },
    { "command": "DrawAbs", "args": [101, 68, 102, 68] },
    { "command": "DrawAbs", "args": [101, 69, 102, 69] },
    { "command": "DrawAbs", "args": [101, 70, 102, 70] },
    { "command": "DrawAbs", "args": [102, 70, 103, 70] },
    { "command": "DrawAbs", "args": [102, 71, 103, 71] },
    { "command": "DrawAbs", "args": [102, 72, 103, 72] },
    { "command": "DrawAbs", "args": [102, 73, 103, 73] },
    { "command": "DrawAbs", "args": [102, 74, 103, 74] },
    { "command": "DrawAbs", "args": [103, 74, 104, 74] },
    { "command": "DrawAbs", "args": [103, 75, 104, 75] },
    { "command": "DrawAbs", "args": [103, 76, 104, 76] },
    { "command": "DrawAbs", "args": [103, 77, 104, 77] },
    { "command": "DrawAbs", "args": [103, 78, 104, 78] },
    { "command": "DrawAbs", "args": [103, 79, 104, 79] },
    { "command": "DrawAbs", "args": [103, 80, 104, 80] },
    { "command": "DrawAbs", "args": [103, 81, 104, 81] },
    { "command": "DrawAbs", "args": [103, 82, 104, 82] },
    { "command": "DrawAbs", "args": [104, 82, 105, 82] },
    { "command": "DrawAbs", "args": [104, 83, 105, 83] },
    { "command": "DrawAbs", "args": [104, 84, 105, 84] },
    { "command": "DrawAbs", "args": [104, 85, 105, 85] },
    { "command": "DrawAbs", "args": [104, 86, 105, 86] },
    { "command": "DrawAbs", "args": [105, 86, 106, 86] },
    { "command": "DrawAbs", "args": [105, 87, 106, 87] },
    { "command": "DrawAbs", "args": [106, 87, 107, 87] },
    { "command": "DrawAbs", "args": [106, 88, 107, 88] },
    { "command": "DrawAbs", "args": [107, 88, 108, 88] },
    { "command": "DrawAbs", "args": [108, 88, 109, 88] },
    { "command": "DrawAbs", "args": [108, 87, 109, 87] },
    { "command": "DrawAbs", "args": [108, 86, 109, 86] },
    { "command": "DrawAbs", "args": [108, 85, 109, 85] },
    { "command": "DrawAbs", "args": [108, 84, 109, 84] },
    { "command": "DrawAbs", "args": [108, 83, 109, 83] },
    { "command": "DrawAbs", "args": [108, 82, 109, 82] },
    { "command": "DrawAbs", "args": [108, 81, 109, 81] },
    { "command": "DrawAbs", "args": [108, 80, 109, 80] },
    { "command": "DrawAbs", "args": [108, 79, 109, 79] },
    { "command": "DrawAbs", "args": [108, 78, 109, 78] },
    { "command": "DrawAbs", "args": [108, 79, 109, 79] },
    { "command": "DrawAbs", "args": [108, 80, 109, 80] },
    { "command": "DrawAbs", "args": [108, 81, 109, 81] },
    { "command": "DrawAbs", "args": [108, 82, 109, 82] },
    { "command": "DrawAbs", "args": [108, 83, 109, 83] },
    { "command": "DrawAbs", "args": [108, 84, 109, 84] },
    { "command": "DrawAbs", "args": [108, 85, 109, 85] },
    { "command": "DrawAbs", "args": [109, 85, 110, 85] },
    { "command": "DrawAbs", "args": [109, 86, 110, 86] },
    { "command": "DrawAbs", "args": [109, 87, 110, 87] },
    { "command": "DrawAbs", "args": [109, 88, 110, 88] },
    { "command": "DrawAbs", "args": [110, 88, 111, 88] },
    { "command": "DrawAbs", "args": [110, 89, 111, 89] },
    { "command": "DrawAbs", "args": [111, 89, 112, 89] },
    { "command": "DrawAbs", "args": [111, 88, 112, 88] },
    { "command": "DrawAbs", "args": [112, 88, 113, 88] },
    { "command": "DrawAbs", "args": [113, 88, 114, 88] },
    { "command": "DrawAbs", "args": [114, 88, 115, 88] },
    { "command": "DrawAbs", "args": [114, 87, 115, 87] },
    { "command": "DrawAbs", "args": [114, 86, 115, 86] },
    { "command": "DrawAbs", "args": [114, 85, 115, 85] },
    { "command": "DrawAbs", "args": [114, 84, 115, 84] },
    { "command": "DrawAbs", "args": [114, 83, 115, 83] },
    { "command": "DrawAbs", "args": [114, 82, 115, 82] },
    { "command": "DrawAbs", "args": [113, 82, 114, 82] },
    { "command": "DrawAbs", "args": [113, 81, 114, 81] },
    { "command": "DrawAbs", "args": [113, 80, 114, 80] },
    { "command": "DrawAbs", "args": [113, 79, 114, 79] },
    { "command": "DrawAbs", "args": [113, 78, 114, 78] },
    { "command": "DrawAbs", "args": [113, 77, 114, 77] },
    { "command": "DrawAbs", "args": [113, 76, 114, 76] },
    { "command": "DrawAbs", "args": [113, 77, 114, 77] },
    { "command": "DrawAbs", "args": [114, 77, 115, 77] },
    { "command": "DrawAbs", "args": [114, 78, 115, 78] },
    { "command": "DrawAbs", "args": [115, 78, 116, 78] },
    { "command": "DrawAbs", "args": [115, 79, 116, 79] },
    { "command": "DrawAbs", "args": [116, 79, 117, 79] },
    { "command": "DrawAbs", "args": [117, 79, 118, 79] },
    { "command": "DrawAbs", "args": [117, 78, 118, 78] },
    { "command": "DrawAbs", "args": [117, 77, 118, 77] },
    { "command": "DrawAbs", "args": [118, 77, 119, 77] },
    { "command": "DrawAbs", "args": [118, 76, 119, 76] },
    { "command": "DrawAbs", "args": [119, 75, 120, 75] },
    { "command": "DrawAbs", "args": [120, 75, 121, 75] },
    { "command": "DrawAbs", "args": [120, 76, 121, 76] },
    { "command": "DrawAbs", "args": [119, 76, 120, 76] },
    { "command": "DrawAbs", "args": [119, 77, 120, 77] },
    { "command": "DrawAbs", "args": [119, 78, 120, 78] },
    { "command": "DrawAbs", "args": [119, 79, 120, 79] },
    { "command": "DrawAbs", "args": [119, 80, 120, 80] },
    { "command": "DrawAbs", "args": [119, 81, 120, 81] },
    { "command": "DrawAbs", "args": [119, 82, 120, 82] },
    { "command": "DrawAbs", "args": [119, 83, 120, 83] },
    { "command": "DrawAbs", "args": [119, 84, 120, 84] },
    { "command": "DrawAbs", "args": [119, 85, 120, 85] },
    { "command": "DrawAbs", "args": [119, 86, 120, 86] },
    { "command": "DrawAbs", "args": [120, 86, 121, 86] },
    { "command": "DrawAbs", "args": [120, 87, 121, 87] },
    { "command": "DrawAbs", "args": [121, 87, 122, 87] },
    { "command": "DrawAbs", "args": [122, 87, 123, 87] },
    { "command": "DrawAbs", "args": [122, 86, 123, 86] },
    { "command": "DrawAbs", "args": [123, 85, 124, 85] },
    { "command": "DrawAbs", "args": [123, 84, 124, 84] },
    { "command": "DrawAbs", "args": [123, 83, 124, 83] },
    { "command": "DrawAbs", "args": [124, 82, 125, 82] },
    { "command": "DrawAbs", "args": [124, 81, 125, 81] },
    { "command": "DrawAbs", "args": [124, 80, 125, 80] },
    { "command": "DrawAbs", "args": [124, 79, 125, 79] },
    { "command": "DrawAbs", "args": [124, 78, 125, 78] },
    { "command": "DrawAbs", "args": [124, 77, 125, 77] },
    { "command": "DrawAbs", "args": [123, 76, 124, 76] },
    { "command": "DrawAbs", "args": [123, 75, 124, 75] },
    { "command": "DrawAbs", "args": [122, 74, 123, 74] },
    { "command": "DrawAbs", "args": [122, 72, 123, 72] },
    { "command": "DrawAbs", "args": [121, 69, 122, 69] },
    { "command": "DrawAbs", "args": [120, 66, 121, 66] },
    { "command": "DrawAbs", "args": [120, 62, 121, 62] },
    { "command": "DrawAbs", "args": [119, 60, 120, 60] },
    { "command": "DrawAbs", "args": [119, 58, 120, 58] },
    { "command": "DrawAbs", "args": [119, 57, 120, 57] },
    { "command": "DrawAbs", "args": [119, 56, 120, 56] },
    { "command": "DrawAbs", "args": [119, 55, 120, 55] },
    { "command": "DrawAbs", "args": [119, 54, 120, 54] },
    { "command": "DrawAbs", "args": [119, 53, 120, 53] },
    { "command": "DrawAbs", "args": [119, 51, 120, 51] },
    { "command": "DrawAbs", "args": [119, 50, 120, 50] },
    { "command": "DrawAbs", "args": [119, 49, 120, 49] },
    { "command": "PicSetColor", "args": [10] },
    { "command": "DrawAbs", "args": [100, 79, 101, 79] },
    { "command": "DrawAbs", "args": [101, 79, 102, 79] },
    { "command": "DrawAbs", "args": [101, 78, 102, 78] },
    { "command": "DrawAbs", "args": [102, 78, 103, 78] },
    { "command": "DrawAbs", "args": [103, 77, 104, 77] },
    { "command": "DrawAbs", "args": [104, 76, 105, 76] },
    { "command": "DrawAbs", "args": [105, 76, 106, 76] },
    { "command": "DrawAbs", "args": [106, 75, 107, 75] },
    { "command": "DrawAbs", "args": [106, 74, 107, 74] },
    { "command": "DrawAbs", "args": [107, 74, 108, 74] },
    { "command": "DrawAbs", "args": [108, 74, 109, 74] },
    { "command": "DrawAbs", "args": [108, 73, 109, 73] },
    { "command": "DrawAbs", "args": [109, 73, 110, 73] },
    { "command": "DrawAbs", "args": [119, 50, 120, 50] },
    { "command": "DrawAbs", "args": [119, 51, 120, 51] },
    { "command": "DrawAbs", "args": [119, 52, 120, 52] },
    { "command": "DrawAbs", "args": [119, 53, 120, 53] },
    { "command": "DrawAbs", "args": [120, 53, 121, 53] },
    { "command": "DrawAbs", "args": [120, 54, 121, 54] },
    { "command": "DrawAbs", "args": [120, 55, 121, 55] },
    { "command": "DrawAbs", "args": [120, 56, 121, 56] },
    { "command": "DrawAbs", "args": [120, 57, 121, 57] },
    { "command": "DrawAbs", "args": [121, 57, 122, 57] },
    { "command": "DrawAbs", "args": [121, 58, 122, 58] },
    { "command": "DrawAbs", "args": [121, 59, 122, 59] },
    { "command": "DrawAbs", "args": [121, 60, 122, 60] },
    { "command": "DrawAbs", "args": [121, 61, 122, 61] },
    { "command": "DrawAbs", "args": [121, 62, 122, 62] },
    { "command": "DrawAbs", "args": [121, 63, 122, 63] },
    { "command": "DrawAbs", "args": [121, 64, 122, 64] },
    { "command": "DrawAbs", "args": [121, 65, 122, 65] },
    { "command": "DrawAbs", "args": [121, 66, 122, 66] },
    { "command": "DrawAbs", "args": [121, 67, 122, 67] },
    { "command": "DrawAbs", "args": [121, 68, 122, 68] },
    { "command": "DrawAbs", "args": [121, 69, 122, 69] },
    { "command": "DrawAbs", "args": [122, 69, 123, 69] },
    { "command": "DrawAbs", "args": [122, 70, 123, 70] },
    { "command": "DrawAbs", "args": [122, 71, 123, 71] },
    { "command": "DrawAbs", "args": [122, 72, 123, 72] },
    { "command": "DrawAbs", "args": [122, 73, 123, 73] },
    { "command": "DrawAbs", "args": [122, 74, 123, 74] },
    { "command": "DrawAbs", "args": [122, 75, 123, 75] },
    { "command": "DrawAbs", "args": [123, 75, 124, 75] },
    { "command": "DrawAbs", "args": [123, 76, 124, 76] },
    { "command": "DrawAbs", "args": [123, 77, 124, 77] },
    { "command": "DrawAbs", "args": [124, 78, 125, 78] },
    { "command": "DrawAbs", "args": [124, 79, 125, 79] },
    { "command": "DrawAbs", "args": [124, 80, 125, 80] },
    { "command": "DrawAbs", "args": [125, 80, 126, 80] },
    { "command": "DrawAbs", "args": [125, 81, 126, 81] },
    { "command": "DrawAbs", "args": [125, 82, 126, 82] },
    { "command": "DrawAbs", "args": [125, 83, 126, 83] },
    { "command": "DrawAbs", "args": [126, 83, 127, 83] },
    { "command": "DrawAbs", "args": [126, 84, 127, 84] },
    { "command": "DrawAbs", "args": [126, 85, 127, 85] },
    { "command": "DrawAbs", "args": [127, 85, 128, 85] },
    { "command": "DrawAbs", "args": [128, 85, 129, 85] },
    { "command": "DrawAbs", "args": [128, 84, 129, 84] },
    { "command": "DrawAbs", "args": [129, 84, 130, 84] },
    { "command": "DrawAbs", "args": [129, 83, 130, 83] },
    { "command": "DrawAbs", "args": [129, 82, 130, 82] },
    { "command": "DrawAbs", "args": [129, 81, 130, 81] },
    { "command": "DrawAbs", "args": [129, 80, 130, 80] },
    { "command": "DrawAbs", "args": [129, 79, 130, 79] },
    { "command": "DrawAbs", "args": [129, 78, 130, 78] },
    { "command": "DrawAbs", "args": [129, 77, 130, 77] },
    { "command": "DrawAbs", "args": [129, 76, 130, 76] },
    { "command": "DrawAbs", "args": [129, 75, 130, 75] },
    { "command": "DrawAbs", "args": [129, 74, 130, 74] },
    { "command": "DrawAbs", "args": [129, 73, 130, 73] },
    { "command": "DrawAbs", "args": [128, 73, 129, 73] },
    { "command": "DrawAbs", "args": [129, 73, 130, 73] },
    { "command": "DrawAbs", "args": [129, 74, 130, 74] },
    { "command": "DrawAbs", "args": [129, 75, 130, 75] },
    { "command": "DrawAbs", "args": [129, 76, 130, 76] },
    { "command": "DrawAbs", "args": [129, 77, 130, 77] },
    { "command": "DrawAbs", "args": [129, 78, 130, 78] },
    { "command": "DrawAbs", "args": [130, 78, 131, 78] },
    { "command": "DrawAbs", "args": [130, 79, 131, 79] },
    { "command": "DrawAbs", "args": [130, 80, 131, 80] },
    { "command": "DrawAbs", "args": [130, 81, 131, 81] },
    { "command": "DrawAbs", "args": [130, 82, 131, 82] },
    { "command": "DrawAbs", "args": [130, 83, 131, 83] },
    { "command": "DrawAbs", "args": [131, 83, 132, 83] },
    { "command": "DrawAbs", "args": [132, 83, 133, 83] },
    { "command": "DrawAbs", "args": [133, 83, 134, 83] },
    { "command": "DrawAbs", "args": [134, 83, 135, 83] },
    { "command": "DrawAbs", "args": [134, 82, 135, 82] },
    { "command": "DrawAbs", "args": [134, 81, 135, 81] },
    { "command": "DrawAbs", "args": [134, 80, 135, 80] },
    { "command": "DrawAbs", "args": [134, 79, 135, 79] },
    { "command": "DrawAbs", "args": [134, 78, 135, 78] },
    { "command": "DrawAbs", "args": [134, 77, 135, 77] },
    { "command": "DrawAbs", "args": [134, 76, 135, 76] },
    { "command": "DrawAbs", "args": [134, 75, 135, 75] },
    { "command": "DrawAbs", "args": [134, 74, 135, 74] },
    { "command": "DrawAbs", "args": [134, 73, 135, 73] },
    { "command": "DrawAbs", "args": [134, 72, 135, 72] },
    { "command": "DrawAbs", "args": [134, 71, 135, 71] },
    { "command": "DrawAbs", "args": [134, 70, 135, 70] },
    { "command": "DrawAbs", "args": [134, 69, 135, 69] },
    { "command": "DrawAbs", "args": [134, 68, 135, 68] },
    { "command": "DrawAbs", "args": [134, 67, 135, 67] },
    { "command": "DrawAbs", "args": [134, 68, 135, 68] },
    { "command": "DrawAbs", "args": [134, 69, 135, 69] },
    { "command": "DrawAbs", "args": [134, 70, 135, 70] },
    { "command": "DrawAbs", "args": [134, 71, 135, 71] },
    { "command": "DrawAbs", "args": [134, 72, 135, 72] },
    { "command": "DrawAbs", "args": [134, 73, 135, 73] },
    { "command": "DrawAbs", "args": [134, 74, 135, 74] },
    { "command": "DrawAbs", "args": [134, 75, 135, 75] },
    { "command": "DrawAbs", "args": [134, 76, 135, 76] },
    { "command": "DrawAbs", "args": [134, 77, 135, 77] },
    { "command": "DrawAbs", "args": [134, 78, 135, 78] },
    { "command": "DrawAbs", "args": [134, 79, 135, 79] },
    { "command": "DrawAbs", "args": [134, 80, 135, 80] },
    { "command": "DrawAbs", "args": [135, 81, 136, 81] },
    { "command": "DrawAbs", "args": [135, 82, 136, 82] },
    { "command": "DrawAbs", "args": [136, 82, 137, 82] },
    { "command": "DrawAbs", "args": [137, 82, 138, 82] },
    { "command": "DrawAbs", "args": [138, 82, 139, 82] },
    { "command": "DrawAbs", "args": [139, 82, 140, 82] },
    { "command": "DrawAbs", "args": [139, 83, 140, 83] },
    { "command": "DrawAbs", "args": [139, 82, 140, 82] },
    { "command": "DrawAbs", "args": [140, 82, 141, 82] },
    { "command": "DrawAbs", "args": [140, 81, 141, 81] },
    { "command": "DrawAbs", "args": [140, 80, 141, 80] },
    { "command": "DrawAbs", "args": [140, 79, 141, 79] },
    { "command": "DrawAbs", "args": [140, 78, 141, 78] },
    { "command": "DrawAbs", "args": [140, 77, 141, 77] },
    { "command": "DrawAbs", "args": [140, 76, 141, 76] },
    { "command": "DrawAbs", "args": [139, 75, 140, 75] },
    { "command": "DrawAbs", "args": [139, 74, 140, 74] },
    { "command": "DrawAbs", "args": [139, 73, 140, 73] },
    { "command": "DrawAbs", "args": [138, 73, 139, 73] },
    { "command": "DrawAbs", "args": [138, 72, 139, 72] },
    { "command": "DrawAbs", "args": [138, 71, 139, 71] },
    { "command": "DrawAbs", "args": [137, 71, 138, 71] },
    { "command": "DrawAbs", "args": [137, 70, 138, 70] },
    { "command": "DrawAbs", "args": [136, 69, 137, 69] },
    { "command": "DrawAbs", "args": [136, 68, 137, 68] },
    { "command": "DrawAbs", "args": [135, 68, 136, 68] },
    { "command": "DrawAbs", "args": [135, 67, 136, 67] },
    { "command": "DrawAbs", "args": [136, 67, 137, 67] },
    { "command": "DrawAbs", "args": [136, 68, 137, 68] },
    { "command": "DrawAbs", "args": [137, 68, 138, 68] },
    { "command": "DrawAbs", "args": [137, 67, 138, 67] },
    { "command": "DrawAbs", "args": [137, 66, 138, 66] },
    { "command": "DrawAbs", "args": [138, 66, 139, 66] },
    { "command": "DrawAbs", "args": [138, 65, 139, 65] },
    { "command": "DrawAbs", "args": [138, 64, 139, 64] },
    { "command": "DrawAbs", "args": [139, 63, 140, 63] },
    { "command": "DrawAbs", "args": [139, 62, 140, 62] },
    { "command": "DrawAbs", "args": [139, 61, 140, 61] },
    { "command": "DrawAbs", "args": [139, 60, 140, 60] },
    { "command": "DrawAbs", "args": [139, 59, 140, 59] },
    { "command": "DrawAbs", "args": [139, 58, 140, 58] },
    { "command": "DrawAbs", "args": [138, 58, 139, 58] },
    { "command": "DrawAbs", "args": [138, 57, 139, 57] },
    { "command": "DrawAbs", "args": [138, 56, 139, 56] },
    { "command": "DrawAbs", "args": [137, 56, 138, 56] },
    { "command": "DrawAbs", "args": [129, 66, 130, 66] },
    { "command": "DrawAbs", "args": [129, 67, 130, 67] },
    { "command": "DrawAbs", "args": [129, 66, 130, 66] },
    { "command": "DrawAbs", "args": [129, 65, 130, 65] },
    { "command": "DrawAbs", "args": [129, 64, 130, 64] },
    { "command": "DrawAbs", "args": [129, 63, 130, 63] },
    { "command": "DrawAbs", "args": [130, 63, 131, 63] },
    { "command": "DrawAbs", "args": [130, 64, 131, 64] },
    { "command": "DrawAbs", "args": [131, 64, 132, 64] },
    { "command": "DrawAbs", "args": [131, 65, 132, 65] },
    { "command": "DrawAbs", "args": [131, 66, 132, 66] },
    { "command": "DrawAbs", "args": [130, 66, 131, 66] },
    { "command": "DrawAbs", "args": [130, 65, 131, 65] },
    { "command": "DrawAbs", "args": [129, 65, 130, 65] },
    { "command": "DrawAbs", "args": [129, 64, 130, 64] },
    { "command": "DrawAbs", "args": [129, 63, 130, 63] },
    { "command": "PicSetColor", "args": [0] },
    { "command": "DrawAbs", "args": [101, 82, 102, 82] },
    { "command": "DrawAbs", "args": [101, 81, 102, 81] },
    { "command": "DrawAbs", "args": [101, 80, 102, 80] },
    { "command": "DrawAbs", "args": [100, 80, 101, 80] },
    { "command": "DrawAbs", "args": [101, 86, 102, 86] },
    { "command": "DrawAbs", "args": [102, 86, 103, 86] },
    { "command": "DrawAbs", "args": [101, 86, 102, 86] },
    { "command": "DrawAbs", "args": [102, 86, 103, 86] },
    { "command": "DrawAbs", "args": [102, 85, 103, 85] },
    { "command": "DrawAbs", "args": [102, 84, 103, 84] },
    { "command": "DrawAbs", "args": [102, 83, 103, 83] },
    { "command": "DrawAbs", "args": [101, 83, 102, 83] },
    { "command": "DrawAbs", "args": [101, 76, 102, 76] },
    { "command": "DrawAbs", "args": [134, 69, 135, 69] },
    { "command": "DrawAbs", "args": [134, 68, 135, 68] },
    { "command": "DrawAbs", "args": [133, 68, 134, 68] },
    { "command": "DrawAbs", "args": [133, 67, 134, 67] },
    { "command": "DrawAbs", "args": [134, 67, 135, 67] },
    { "command": "DrawAbs", "args": [133, 67, 134, 67] },
    { "command": "DrawAbs", "args": [133, 68, 134, 68] },
    { "command": "DrawAbs", "args": [133, 69, 134, 69] },
    { "command": "DrawAbs", "args": [133, 70, 134, 70] },
    { "command": "DrawAbs", "args": [133, 71, 134, 71] },
    { "command": "DrawAbs", "args": [133, 72, 134, 72] },
    { "command": "DrawAbs", "args": [133, 73, 134, 73] },
    { "command": "DrawAbs", "args": [133, 82, 134, 82] },
    { "command": "DrawAbs", "args": [119, 68, 120, 68] },
    { "command": "DrawAbs", "args": [120, 68, 121, 68] },
    { "command": "DrawAbs", "args": [120, 67, 121, 67] },
    { "command": "DrawAbs", "args": [120, 66, 121, 66] },
    { "command": "DrawAbs", "args": [119, 66, 120, 66] },
    { "command": "DrawAbs", "args": [119, 65, 120, 65] },
    { "command": "DrawAbs", "args": [119, 64, 120, 64] },
    { "command": "DrawAbs", "args": [119, 63, 120, 63] },
    { "command": "DrawAbs", "args": [118, 63, 119, 63] },
    { "command": "DrawAbs", "args": [118, 62, 119, 62] },
    { "command": "DrawAbs", "args": [119, 62, 120, 62] },
    { "command": "DrawAbs", "args": [118, 62, 119, 62] },
    { "command": "DrawAbs", "args": [118, 63, 119, 63] },
    { "command": "DrawAbs", "args": [118, 64, 119, 64] },
    { "command": "DrawAbs", "args": [119, 64, 120, 64] },
    { "command": "DrawAbs", "args": [119, 65, 120, 65] },
    { "command": "DrawAbs", "args": [119, 66, 120, 66] },
    { "command": "DrawAbs", "args": [119, 67, 120, 67] },
    { "command": "DrawAbs", "args": [120, 67, 121, 67] },
    { "command": "DrawAbs", "args": [120, 68, 121, 68] },
    { "command": "DrawAbs", "args": [120, 69, 121, 69] },
    { "command": "DrawAbs", "args": [120, 70, 121, 70] },
    { "command": "DrawAbs", "args": [120, 69, 121, 69] },
    { "command": "DrawAbs", "args": [118, 56, 119, 56] },
    { "command": "DrawAbs", "args": [118, 57, 119, 57] },
    { "command": "DrawAbs", "args": [118, 58, 119, 58] },
    { "command": "DrawAbs", "args": [118, 59, 119, 59] },
    { "command": "DrawAbs", "args": [118, 60, 119, 60] },
    { "command": "DrawAbs", "args": [118, 61, 119, 61] },
    { "command": "DrawAbs", "args": [119, 61, 120, 61] },
    { "command": "DrawAbs", "args": [119, 60, 120, 60] },
    { "command": "DrawAbs", "args": [120, 60, 121, 60] },
    { "command": "DrawAbs", "args": [119, 60, 120, 60] },
    { "command": "DrawAbs", "args": [118, 51, 119, 51] },
    { "command": "DrawAbs", "args": [119, 52, 120, 52] },
    { "command": "DrawAbs", "args": [119, 53, 120, 53] },
    { "command": "DrawAbs", "args": [119, 54, 120, 54] },
    { "command": "DrawAbs", "args": [119, 55, 120, 55] },
    { "command": "DrawAbs", "args": [119, 56, 120, 56] },
    { "command": "DrawAbs", "args": [119, 57, 120, 57] },
    { "command": "DrawAbs", "args": [120, 57, 121, 57] },
    { "command": "DrawAbs", "args": [120, 58, 121, 58] },
    { "command": "DrawAbs", "args": [120, 59, 121, 59] },
    { "command": "DrawAbs", "args": [120, 60, 121, 60] },
    { "command": "DrawAbs", "args": [120, 61, 121, 61] },
    { "command": "DrawAbs", "args": [120, 62, 121, 62] },
    { "command": "DrawAbs", "args": [120, 63, 121, 63] },
    { "command": "DrawAbs", "args": [120, 64, 121, 64] },
    { "command": "DrawAbs", "args": [120, 65, 121, 65] },
    { "command": "DrawAbs", "args": [120, 66, 121, 66] },
    { "command": "PicSetColor", "args": [10] },
    { "command": "DrawAbs", "args": [121, 53, 122, 53] },
    { "command": "DrawAbs", "args": [121, 54, 122, 54] },
    { "command": "DrawAbs", "args": [120, 54, 121, 54] },
    { "command": "DrawAbs", "args": [120, 53, 121, 53] },
    { "command": "DrawAbs", "args": [120, 52, 121, 52] },
    { "command": "DrawAbs", "args": [120, 51, 121, 51] },
    { "command": "DrawAbs", "args": [120, 52, 121, 52] },
    { "command": "DrawAbs", "args": [120, 53, 121, 53] },
    { "command": "DrawAbs", "args": [120, 54, 121, 54] },
    { "command": "DrawAbs", "args": [121, 54, 122, 54] },
    { "command": "DrawAbs", "args": [121, 55, 122, 55] },
    { "command": "DrawAbs", "args": [121, 56, 122, 56] },
    { "command": "DrawAbs", "args": [122, 56, 123, 56] },
    { "command": "DrawAbs", "args": [122, 57, 123, 57] },
    { "command": "DrawAbs", "args": [122, 58, 123, 58] },
    { "command": "DrawAbs", "args": [122, 59, 123, 59] },
    { "command": "DrawAbs", "args": [122, 60, 123, 60] },
    { "command": "DrawAbs", "args": [122, 61, 123, 61] },
    { "command": "DrawAbs", "args": [122, 62, 123, 62] },
    { "command": "DrawAbs", "args": [122, 63, 123, 63] },
    { "command": "DrawAbs", "args": [122, 64, 123, 64] },
    { "command": "DrawAbs", "args": [122, 65, 123, 65] },
    { "command": "DrawAbs", "args": [122, 66, 123, 66] },
    { "command": "DrawAbs", "args": [122, 67, 123, 67] },
    { "command": "DrawAbs", "args": [122, 68, 123, 68] },
    { "command": "DrawAbs", "args": [122, 69, 123, 69] },
    { "command": "DrawAbs", "args": [121, 69, 122, 69] },
    { "command": "DrawAbs", "args": [121, 70, 122, 70] },
    { "command": "DrawAbs", "args": [121, 71, 122, 71] },
    { "command": "DrawAbs", "args": [121, 72, 122, 72] },
    { "command": "DrawAbs", "args": [121, 73, 122, 73] },
    { "command": "DrawAbs", "args": [121, 74, 122, 74] },
    { "command": "DrawAbs", "args": [121, 75, 122, 75] },
    { "command": "DrawAbs", "args": [121, 76, 122, 76] },
    { "command": "PicSetColor", "args": [0] },
    { "command": "DrawAbs", "args": [119, 68, 120, 68] },
    { "command": "DrawAbs", "args": [119, 69, 120, 69] },
    { "command": "DrawAbs", "args": [120, 69, 121, 69] },
    { "command": "DrawAbs", "args": [120, 70, 121, 70] },
    { "command": "DrawAbs", "args": [119, 70, 120, 70] },
    { "command": "DrawAbs", "args": [119, 71, 120, 71] },
    { "command": "DrawAbs", "args": [119, 72, 120, 72] },
    { "command": "DrawAbs", "args": [120, 72, 121, 72] },
    { "command": "DrawAbs", "args": [120, 71, 121, 71] },
    { "command": "DrawAbs", "args": [120, 70, 121, 70] },
    { "command": "DrawAbs", "args": [119, 70, 120, 70] },
    { "command": "DrawAbs", "args": [119, 69, 120, 69] },
    { "command": "DrawAbs", "args": [119, 70, 120, 70] },
    { "command": "DrawAbs", "args": [119, 71, 120, 71] },
    { "command": "DrawAbs", "args": [119, 72, 120, 72] },
    { "command": "DrawAbs", "args": [119, 73, 120, 73] },
    { "command": "DrawAbs", "args": [120, 73, 121, 73] },
    { "command": "DrawAbs", "args": [119, 73, 120, 73] },
    { "command": "DrawAbs", "args": [118, 73, 119, 73] },
    { "command": "DrawAbs", "args": [117, 75, 118, 75] },
    { "command": "DrawAbs", "args": [118, 75, 119, 75] },
    { "command": "DrawAbs", "args": [118, 76, 119, 76] },
    { "command": "DrawAbs", "args": [117, 76, 118, 76] },
    { "command": "DrawAbs", "args": [118, 76, 119, 76] },
    { "command": "DrawAbs", "args": [118, 77, 119, 77] },
    { "command": "DrawAbs", "args": [117, 77, 118, 77] },
    { "command": "DrawAbs", "args": [117, 78, 118, 78] },
    { "command": "DrawAbs", "args": [117, 77, 118, 77] },
    { "command": "DrawAbs", "args": [117, 76, 118, 76] },
    { "command": "DrawAbs", "args": [116, 75, 117, 75] },
    { "command": "DrawAbs", "args": [115, 92, 116, 92] },
    { "command": "DrawAbs", "args": [115, 91, 116, 91] },
    { "command": "DrawAbs", "args": [115, 90, 116, 90] },
    { "command": "DrawAbs", "args": [115, 89, 116, 89] },
    { "command": "DrawAbs", "args": [115, 88, 116, 88] },
    { "command": "DrawAbs", "args": [114, 89, 115, 89] },
    { "command": "DrawAbs", "args": [108, 88, 109, 88] },
    { "command": "End", "args": [] }
  ]
}
